Workbook

Sheet מסך ניווט מרכזי
N1: Type | O1: Code | P1: He | Q1: En | R1: Sheet | S1: Cell | T1: Link
B2: CBC ISRAEL | SAP PP-PI - מסך ניווט מרכזי | J2: ★ CBC Project NEO | N2: טרנזקציה | O2: MM01 | P2: Manage Product Master Data | Q2: F1602A | R2: 1. נתוני אב חומר ויחידות מידה ( | S2: A6 | T2: =HYPERLINK("#'"&R2&"'!"&S2,"➜ פתח")
B3: Project NEO - Production Planning for Process Industries | ECC 6.0 ➜ S/4HANA | N3: Fiori | O3: F1602A | P3: Manage Product Master Data | R3: 1. נתוני אב חומר ויחידות מידה ( | S3: A6 | T3: =HYPERLINK("#'"&R3&"'!"&S3,"➜ פתח")
N4: טרנזקציה | O4: MM50 | P4: Manage Product Master Data | Q4: F1602A | R4: 1. נתוני אב חומר ויחידות מידה ( | S4: A7 | T4: =HYPERLINK("#'"&R4&"'!"&S4,"➜ פתח")
B5: סיכום התקדמות מיגרציה (KPI - חי מה-Cockpit) | N5: Fiori | O5: F1602A | P5: Manage Product Master Data | R5: 1. נתוני אב חומר ויחידות מידה ( | S5: A7 | T5: =HYPERLINK("#'"&R5&"'!"&S5,"➜ פתח")
B6: =COUNTA('Cockpit מעקב מיגרציה'!$C$8:$C$72) | C6: =COUNTIF('Cockpit מעקב מיגרציה'!$D$8:$D$72,"Done") | D6: =COUNTIF('Cockpit מעקב מיגרציה'!$D$8:$D$72,"Tested") | E6: =(COUNTIF('Cockpit מעקב מיגרציה'!$D$8:$D$72,"In analysis")+COUNTIF('Cockpit מעקב מיגרציה'!$D$8:$D$72,"In conversion")) | F6: =COUNTIF('Cockpit מעקב מיגרציה'!$D$8:$D$72,"Not started") | G6: =IFERROR((COUNTIF('Cockpit מעקב מיגרציה'!$D$8:$D$72,"Done"))/(COUNTA('Cockpit מעקב מיגרציה'!$C$8:$C$72)),0) | N6: טרנזקציה | O6: MMSC | P6: Mass Maintenance - Products | Q6: - | R6: 1. נתוני אב חומר ויחידות מידה ( | S6: A8 | T6: =HYPERLINK("#'"&R6&"'!"&S6,"➜ פתח")
B7: סה"כ אובייקטים | C7: הושלם | D7: נבדק | E7: בתהליך | F7: פתוח | G7: % השלמה | N7: טרנזקציה | O7: CUNI | P7: Configure Units of Measure (SPRO) | Q7: - | R7: 1. נתוני אב חומר ויחידות מידה ( | S7: A9 | T7: =HYPERLINK("#'"&R7&"'!"&S7,"➜ פתח")
N8: BAPI | O8: BAPI_MATERIAL_SAVEDATA | P8: יצירה/עדכון אב חומר - ליבת הטעינה ההמונית והממשקים | R8: 1. נתוני אב חומר ויחידות מידה ( | S8: A12 | T8: =HYPERLINK("#'"&R8&"'!"&S8,"➜ פתח")
B9: ניווט מהיר לגיליונות | N9: BAPI | O9: BAPI_MATERIAL_GET_DETAIL | P9: שליפת נתוני חומר לדוחות/ממשקים | R9: 1. נתוני אב חומר ויחידות מידה ( | S9: A13 | T9: =HYPERLINK("#'"&R9&"'!"&S9,"➜ פתח")
B10: 1. נתוני אב חומר ויחידות מידה (Material & UoM) | D10: 2. עץ מוצר (BOM) | F10: 3. מתכון ייצור ופעולות (Master Recipe) | H10: 4. גרסאות ייצור (Production Versions - חובה ב-S/4) | N10: IDoc | O10: MATMAS (MATMAS05) | P10: הפצת אב חומר ל/מ-מערכות חיצוניות (Zetes/Daymax) | R10: 1. נתוני אב חומר ויחידות מידה ( | S10: A14 | T10: =HYPERLINK("#'"&R10&"'!"&S10,"➜ פתח")
N11: RFC | O11: MARA_SINGLE_READ / MARC_SINGLE_READ | P11: קריאת חומר/מפעל בודד | R11: 1. נתוני אב חומר ויחידות מידה ( | S11: A15 | T11: =HYPERLINK("#'"&R11&"'!"&S11,"➜ פתח")
N12: תוכנית | O12: RMMG2000 | P12: טעינה/עדכון חומר המוני (Direct Input) | R12: 1. נתוני אב חומר ויחידות מידה ( | S12: A18 | T12: =HYPERLINK("#'"&R12&"'!"&S12,"➜ פתח")
B13: 5. משאבים / מרכזי עבודה (Resources) | D13: 6. פק"ע ייצור ומתכון בקרה (Process Order) | F13: 7. קונפיגורציה (Customizing) | H13: ◆ Cockpit מעקב מיגרציה | N13: תוכנית | O13: RMDATIND | P13: Direct Input לאב חומר מממשק | R13: 1. נתוני אב חומר ויחידות מידה ( | S13: A19 | T13: =HYPERLINK("#'"&R13&"'!"&S13,"➜ פתח")
N14: תוכנית | O14: RMMM00B0 / MM60 | P14: דוח רשימת חומרים | R14: 1. נתוני אב חומר ויחידות מידה ( | S14: A20 | T14: =HYPERLINK("#'"&R14&"'!"&S14,"➜ פתח")
N15: טבלה | O15: MARA | P15: נתוני אב חומר כלליים | Q15: General material data | R15: 1. נתוני אב חומר ויחידות מידה ( | S15: A22 | T15: =HYPERLINK("#'"&R15&"'!"&S15,"➜ פתח")
B16: ⇄ ER - Join Map | N16: שדה | O16: MATNR | P16: מספר חומר | Q16: Material number | R16: 1. נתוני אב חומר ויחידות מידה ( | S16: C23 | T16: =HYPERLINK("#'"&R16&"'!"&S16,"➜ פתח")
N17: שדה | O17: MTART | P17: סוג חומר | Q17: Material type | R17: 1. נתוני אב חומר ויחידות מידה ( | S17: C24 | T17: =HYPERLINK("#'"&R17&"'!"&S17,"➜ פתח")
N18: שדה | O18: MEINS | P18: יחידת מידה בסיסית | Q18: Base unit of measure | R18: 1. נתוני אב חומר ויחידות מידה ( | S18: C25 | T18: =HYPERLINK("#'"&R18&"'!"&S18,"➜ פתח")
N19: שדה | O19: MATKL | P19: קבוצת חומר | Q19: Material group | R19: 1. נתוני אב חומר ויחידות מידה ( | S19: C26 | T19: =HYPERLINK("#'"&R19&"'!"&S19,"➜ פתח")
N20: שדה | O20: GROES | P20: גודל / מידות | Q20: Size / dimensions | R20: 1. נתוני אב חומר ויחידות מידה ( | S20: C27 | T20: =HYPERLINK("#'"&R20&"'!"&S20,"➜ פתח")
N21: שדה | O21: BRGEW | P21: משקל ברוטו | Q21: Gross weight | R21: 1. נתוני אב חומר ויחידות מידה ( | S21: C28 | T21: =HYPERLINK("#'"&R21&"'!"&S21,"➜ פתח")
N22: שדה | O22: NTGEW | P22: משקל נטו | Q22: Net weight | R22: 1. נתוני אב חומר ויחידות מידה ( | S22: C29 | T22: =HYPERLINK("#'"&R22&"'!"&S22,"➜ פתח")
N23: שדה | O23: XCHPF | P23: ניהול אצוות | Q23: Batch management indicator | R23: 1. נתוני אב חומר ויחידות מידה ( | S23: C30 | T23: =HYPERLINK("#'"&R23&"'!"&S23,"➜ פתח")
B24: 🔍 חיפוש גלובלי (טבלה / שדה / טרנזקציה - עברית/אנגלית) | N24: טרנזקציה | O24: MM01 | P24: נתוני אב חומר כלליים | Q24: General material data | R24: 1. נתוני אב חומר ויחידות מידה ( | S24: A23 | T24: =HYPERLINK("#'"&R24&"'!"&S24,"➜ פתח")
B25: הקלד כאן: | N25: טרנזקציה | O25: MM02 | P25: נתוני אב חומר כלליים | Q25: General material data | R25: 1. נתוני אב חומר ויחידות מידה ( | S25: A23 | T25: =HYPERLINK("#'"&R25&"'!"&S25,"➜ פתח")
N26: טרנזקציה | O26: MM03 | P26: נתוני אב חומר כלליים | Q26: General material data | R26: 1. נתוני אב חומר ויחידות מידה ( | S26: A23 | T26: =HYPERLINK("#'"&R26&"'!"&S26,"➜ פתח")
B27: קישור | C27: קוד | D27: עברית | E27: English | F27: גיליון | G27: תא | N27: טרנזקציה | O27: MM50 | P27: נתוני אב חומר כלליים | Q27: General material data | R27: 1. נתוני אב חומר ויחידות מידה ( | S27: A23 | T27: =HYPERLINK("#'"&R27&"'!"&S27,"➜ פתח")
B28: =IF(C25="","הקלד מונח וקבל תוצאות מיידיות...",IFERROR(_xlfn._xlws.FILTER(CHOOSE({1,2,3,4,5,6},$T$2:$T$649,$O$2:$O$649,$P$2:$P$649,$Q$2:$Q$649,$R$2:$R$649,$S$2:$S$649),(ISNUMBER(SEARCH(C25,$O$2:$O$649)))+(ISNUMBER(SEARCH(C25,$P$2:$P$649)))+(ISNUMBER(SEARCH(C25,$Q$2:$Q$649)))+(ISNUMBER(SEARCH(C25,$N$2:$N$649)))>0),"לא נמצאו תוצאות")) | N28: טרנזקציה | O28: MMSC | P28: נתוני אב חומר כלליים | Q28: General material data | R28: 1. נתוני אב חומר ויחידות מידה ( | S28: A23 | T28: =HYPERLINK("#'"&R28&"'!"&S28,"➜ פתח")
N29: טבלה | O29: MAKT | P29: תיאורי חומר (טקסטים) | Q29: Material descriptions | R29: 1. נתוני אב חומר ויחידות מידה ( | S29: A32 | T29: =HYPERLINK("#'"&R29&"'!"&S29,"➜ פתח")
N30: שדה | O30: MATNR | P30: מספר חומר | Q30: Material number | R30: 1. נתוני אב חומר ויחידות מידה ( | S30: C33 | T30: =HYPERLINK("#'"&R30&"'!"&S30,"➜ פתח")
N31: שדה | O31: SPRAS | P31: שפה | Q31: Language key | R31: 1. נתוני אב חומר ויחידות מידה ( | S31: C34 | T31: =HYPERLINK("#'"&R31&"'!"&S31,"➜ פתח")
N32: שדה | O32: MAKTX | P32: תיאור חומר | Q32: Material description | R32: 1. נתוני אב חומר ויחידות מידה ( | S32: C35 | T32: =HYPERLINK("#'"&R32&"'!"&S32,"➜ פתח")
N33: שדה | O33: MAKTG | P33: תיאור (אותיות גדולות) | Q33: Description (upper case) | R33: 1. נתוני אב חומר ויחידות מידה ( | S33: C36 | T33: =HYPERLINK("#'"&R33&"'!"&S33,"➜ פתח")
N34: טרנזקציה | O34: MM01 | P34: תיאורי חומר (טקסטים) | Q34: Material descriptions | R34: 1. נתוני אב חומר ויחידות מידה ( | S34: A33 | T34: =HYPERLINK("#'"&R34&"'!"&S34,"➜ פתח")
N35: טרנזקציה | O35: MM02 | P35: תיאורי חומר (טקסטים) | Q35: Material descriptions | R35: 1. נתוני אב חומר ויחידות מידה ( | S35: A33 | T35: =HYPERLINK("#'"&R35&"'!"&S35,"➜ פתח")
N36: טרנזקציה | O36: MM03 | P36: תיאורי חומר (טקסטים) | Q36: Material descriptions | R36: 1. נתוני אב חומר ויחידות מידה ( | S36: A33 | T36: =HYPERLINK("#'"&R36&"'!"&S36,"➜ פתח")
N37: טבלה | O37: MARC | P37: נתוני חומר ברמת מפעל | Q37: Plant data for material | R37: 1. נתוני אב חומר ויחידות מידה ( | S37: A38 | T37: =HYPERLINK("#'"&R37&"'!"&S37,"➜ פתח")
N38: שדה | O38: MATNR | P38: מספר חומר | Q38: Material number | R38: 1. נתוני אב חומר ויחידות מידה ( | S38: C39 | T38: =HYPERLINK("#'"&R38&"'!"&S38,"➜ פתח")
N39: שדה | O39: WERKS | P39: מפעל | Q39: Plant | R39: 1. נתוני אב חומר ויחידות מידה ( | S39: C40 | T39: =HYPERLINK("#'"&R39&"'!"&S39,"➜ פתח")
N40: שדה | O40: DISPO | P40: אחראי MRP | Q40: MRP controller | R40: 1. נתוני אב חומר ויחידות מידה ( | S40: C41 | T40: =HYPERLINK("#'"&R40&"'!"&S40,"➜ פתח")
... N55: שדה | O55: INSME | P55: מלאי בבדיקת איכות | Q55: Stock in quality inspection | R55: 1. נתוני אב חומר ויחידות מידה ( | S55: C53 | T55: =HYPERLINK("#'"&R55&"'!"&S55,"➜ פתח")
B56: פורטל זה הוא .xlsx נקי (ללא מאקרו/גרפים) - בטוח למייל ארגוני. עדכן סטטוס ב-Cockpit וה-KPI יתעדכן מיד. להוספת כפתור חיפוש-מאקרו: הדבק pppi_modPM.bas דרך Alt+F11 ושמור כ-.xlsm. גם זמין כפורטל ווב: index_pppi.html. | N56: טרנזקציה | O56: MMBE | P56: נתוני חומר ברמת מחסן/מלאי | Q56: Storage location / stock data | R56: 1. נתוני אב חומר ויחידות מידה ( | S56: A49 | T56: =HYPERLINK("#'"&R56&"'!"&S56,"➜ פתח")
N57: טרנזקציה | O57: MB52 | P57: נתוני חומר ברמת מחסן/מלאי | Q57: Storage location / stock data | R57: 1. נתוני אב חומר ויחידות מידה ( | S57: A49 | T57: =HYPERLINK("#'"&R57&"'!"&S57,"➜ פתח")
N58: טבלה | O58: MARM | P58: המרות יחידות מידה חלופיות | Q58: Units of measure conversions | R58: 1. נתוני אב חומר ויחידות מידה ( | S58: A55 | T58: =HYPERLINK("#'"&R58&"'!"&S58,"➜ פתח")
N59: שדה | O59: MATNR | P59: מספר חומר | Q59: Material number | R59: 1. נתוני אב חומר ויחידות מידה ( | S59: C56 | T59: =HYPERLINK("#'"&R59&"'!"&S59,"➜ פתח")
N60: שדה | O60: MEINH | P60: יחידת מידה חלופית | Q60: Alternative unit of measure | R60: 1. נתוני אב חומר ויחידות מידה ( | S60: C57 | T60: =HYPERLINK("#'"&R60&"'!"&S60,"➜ פתח")
N61: שדה | O61: UMREZ | P61: מונה להמרה | Q61: Numerator for conversion | R61: 1. נתוני אב חומר ויחידות מידה ( | S61: C58 | T61: =HYPERLINK("#'"&R61&"'!"&S61,"➜ פתח")
N62: שדה | O62: UMREN | P62: מכנה להמרה | Q62: Denominator for conversion | R62: 1. נתוני אב חומר ויחידות מידה ( | S62: C59 | T62: =HYPERLINK("#'"&R62&"'!"&S62,"➜ פתח")
N63: שדה | O63: EAN11 | P63: ברקוד בינלאומי | Q63: International article number (EAN/UPC) | R63: 1. נתוני אב חומר ויחידות מידה ( | S63: C60 | T63: =HYPERLINK("#'"&R63&"'!"&S63,"➜ פתח")
N64: שדה | O64: MESUB | P64: יחידה ברמה הנמוכה | Q64: Lowest level UoM | R64: 1. נתוני אב חומר ויחידות מידה ( | S64: C61 | T64: =HYPERLINK("#'"&R64&"'!"&S64,"➜ פתח")
N65: טרנזקציה | O65: MM02 (תצוגת UoM) | P65: המרות יחידות מידה חלופיות | Q65: Units of measure conversions | R65: 1. נתוני אב חומר ויחידות מידה ( | S65: A56 | T65: =HYPERLINK("#'"&R65&"'!"&S65,"➜ פתח")
N66: טבלה | O66: MEAN | P66: ברקודים / EAN לחומר | Q66: International article numbers (EANs) | R66: 1. נתוני אב חומר ויחידות מידה ( | S66: A63 | T66: =HYPERLINK("#'"&R66&"'!"&S66,"➜ פתח")
N67: שדה | O67: MATNR | P67: מספר חומר | Q67: Material number | R67: 1. נתוני אב חומר ויחידות מידה ( | S67: C64 | T67: =HYPERLINK("#'"&R67&"'!"&S67,"➜ פתח")
N68: שדה | O68: MEINH | P68: יחידת מידה | Q68: Unit of measure | R68: 1. נתוני אב חומר ויחידות מידה ( | S68: C65 | T68: =HYPERLINK("#'"&R68&"'!"&S68,"➜ פתח")
... N149: טרנזקציה | O149: CS01 | P149: Maintain Bill of Material | Q149: F1743 | R149: 2. עץ מוצר (BOM) | S149: A6 | T149: =HYPERLINK("#'"&R149&"'!"&S149,"➜ פתח")
N150: Fiori | O150: F1743 | P150: Maintain Bill of Material | R150: 2. עץ מוצר (BOM) | S150: A6 | T150: =HYPERLINK("#'"&R150&"'!"&S150,"➜ פתח")
N151: טרנזקציה | O151: CS11 | P151: Manage Material BOMs | Q151: F1813 | R151: 2. עץ מוצר (BOM) | S151: A7 | T151: =HYPERLINK("#'"&R151&"'!"&S151,"➜ פתח")
N152: Fiori | O152: F1813 | P152: Manage Material BOMs | R152: 2. עץ מוצר (BOM) | S152: A7 | T152: =HYPERLINK("#'"&R152&"'!"&S152,"➜ פתח")
N153: טרנזקציה | O153: CEWB | P153: Manage Bill of Materials | Q153: F1813 | R153: 2. עץ מוצר (BOM) | S153: A8 | T153: =HYPERLINK("#'"&R153&"'!"&S153,"➜ פתח")
N154: Fiori | O154: F1813 | P154: Manage Bill of Materials | R154: 2. עץ מוצר (BOM) | S154: A8 | T154: =HYPERLINK("#'"&R154&"'!"&S154,"➜ פתח")
N155: BAPI | O155: BAPI_MATERIAL_BOM_GROUP_CREATE | P155: יצירת עץ מוצר (S/4 BOM API) | R155: 2. עץ מוצר (BOM) | S155: A11 | T155: =HYPERLINK("#'"&R155&"'!"&S155,"➜ פתח")
N156: FM | O156: CSAP_MAT_BOM_MAINTAIN | P156: תחזוקת עץ מוצר (ECC) | R156: 2. עץ מוצר (BOM) | S156: A12 | T156: =HYPERLINK("#'"&R156&"'!"&S156,"➜ פתח")
N157: IDoc | O157: BOMMAT | P157: הפצת עץ מוצר חומר בין מערכות | R157: 2. עץ מוצר (BOM) | S157: A13 | T157: =HYPERLINK("#'"&R157&"'!"&S157,"➜ פתח")
N158: RFC | O158: CS_BOM_EXPL_MAT_RC1 | P158: פיצוץ עץ מוצר לחומר | R158: 2. עץ מוצר (BOM) | S158: A14 | T158: =HYPERLINK("#'"&R158&"'!"&S158,"➜ פתח")
N159: תוכנית | O159: RCSBOM00 | P159: עיבוד/בדיקת עצי מוצר המוני | R159: 2. עץ מוצר (BOM) | S159: A17 | T159: =HYPERLINK("#'"&R159&"'!"&S159,"➜ פתח")
N160: תוכנית | O160: RCSBI010 | P160: פיצוץ עץ מוצר רב-רמתי | R160: 2. עץ מוצר (BOM) | S160: A18 | T160: =HYPERLINK("#'"&R160&"'!"&S160,"➜ פתח")
N161: תוכנית | O161: CS_BT | P161: דוח Where-Used לרכיב | R161: 2. עץ מוצר (BOM) | S161: A19 | T161: =HYPERLINK("#'"&R161&"'!"&S161,"➜ פתח")
N162: טבלה | O162: MAST | P162: קישור חומר לעץ מוצר | Q162: Material to BOM link | R162: 2. עץ מוצר (BOM) | S162: A21 | T162: =HYPERLINK("#'"&R162&"'!"&S162,"➜ פתח")
N163: שדה | O163: MATNR | P163: מספר חומר | Q163: Material number | R163: 2. עץ מוצר (BOM) | S163: C22 | T163: =HYPERLINK("#'"&R163&"'!"&S163,"➜ פתח")
N164: שדה | O164: WERKS | P164: מפעל | Q164: Plant | R164: 2. עץ מוצר (BOM) | S164: C23 | T164: =HYPERLINK("#'"&R164&"'!"&S164,"➜ פתח")
N165: שדה | O165: STLAN | P165: שימוש עץ מוצר | Q165: BOM usage (1=Production) | R165: 2. עץ מוצר (BOM) | S165: C24 | T165: =HYPERLINK("#'"&R165&"'!"&S165,"➜ פתח")
N166: שדה | O166: STLNR | P166: מספר עץ מוצר | Q166: Bill of material number | R166: 2. עץ מוצר (BOM) | S166: C25 | T166: =HYPERLINK("#'"&R166&"'!"&S166,"➜ פתח")
N167: שדה | O167: STLAL | P167: חלופת עץ מוצר | Q167: Alternative BOM | R167: 2. עץ מוצר (BOM) | S167: C26 | T167: =HYPERLINK("#'"&R167&"'!"&S167,"➜ פתח")
N168: טרנזקציה | O168: CS01 | P168: קישור חומר לעץ מוצר | Q168: Material to BOM link | R168: 2. עץ מוצר (BOM) | S168: A22 | T168: =HYPERLINK("#'"&R168&"'!"&S168,"➜ פתח")
N169: טרנזקציה | O169: CS02 | P169: קישור חומר לעץ מוצר | Q169: Material to BOM link | R169: 2. עץ מוצר (BOM) | S169: A22 | T169: =HYPERLINK("#'"&R169&"'!"&S169,"➜ פתח")
N170: טרנזקציה | O170: CS03 | P170: קישור חומר לעץ מוצר | Q170: Material to BOM link | R170: 2. עץ מוצר (BOM) | S170: A22 | T170: =HYPERLINK("#'"&R170&"'!"&S170,"➜ פתח")
N171: טבלה | O171: STKO | P171: כותרת עץ מוצר | Q171: BOM header | R171: 2. עץ מוצר (BOM) | S171: A28 | T171: =HYPERLINK("#'"&R171&"'!"&S171,"➜ פתח")
N172: שדה | O172: STLTY | P172: קטגוריית עץ מוצר | Q172: BOM category | R172: 2. עץ מוצר (BOM) | S172: C29 | T172: =HYPERLINK("#'"&R172&"'!"&S172,"➜ פתח")
N173: שדה | O173: STLNR | P173: מספר עץ מוצר | Q173: Bill of material number | R173: 2. עץ מוצר (BOM) | S173: C30 | T173: =HYPERLINK("#'"&R173&"'!"&S173,"➜ פתח")
... N220: טרנזקציה | O220: COIO | P220: Process Order Information System | Q220: - | R220: 3. מתכון ייצור ופעולות (Master | S220: A8 | T220: =HYPERLINK("#'"&R220&"'!"&S220,"➜ פתח")
N221: RFC | O221: CP_RECIPE_READ | P221: קריאת מתכון ייצור | R221: 3. מתכון ייצור ופעולות (Master | S221: A11 | T221: =HYPERLINK("#'"&R221&"'!"&S221,"➜ פתח")
N222: BAPI | O222: BAPI_CENTRAL_CHARACT_CREATE | P222: יצירת מאפיין בדיקה ראשי (QM) | R222: 3. מתכון ייצור ופעולות (Master | S222: A12 | T222: =HYPERLINK("#'"&R222&"'!"&S222,"➜ פתח")
N223: IDoc | O223: LOIPRO | P223: הוראות ייצור - מהמתכון לפק"ע ולקו | R223: 3. מתכון ייצור ופעולות (Master | S223: A13 | T223: =HYPERLINK("#'"&R223&"'!"&S223,"➜ פתח")
N224: PI | O224: Control Recipe / PI Sheet (PI Messages) | P224: שליחת הוראות תהליך לבקר/MES (Zetes/Daymax) | R224: 3. מתכון ייצור ופעולות (Master | S224: A14 | T224: =HYPERLINK("#'"&R224&"'!"&S224,"➜ פתח")
N225: תוכנית | O225: RCEXMASS | P225: עיבוד המוני מתכונים | R225: 3. מתכון ייצור ופעולות (Master | S225: A17 | T225: =HYPERLINK("#'"&R225&"'!"&S225,"➜ פתח")
N226: תוכנית | O226: RCPRECIPE | P226: דוח/הערכת מתכונים | R226: 3. מתכון ייצור ופעולות (Master | S226: A18 | T226: =HYPERLINK("#'"&R226&"'!"&S226,"➜ פתח")
N227: תוכנית | O227: RCO_CONTROL_RECIPE | P227: יצירת/שליחת Control Recipe | R227: 3. מתכון ייצור ופעולות (Master | S227: A19 | T227: =HYPERLINK("#'"&R227&"'!"&S227,"➜ פתח")
N228: טבלה | O228: PLKO | P228: כותרת מתכון ייצור / רשימת פעולות | Q228: Task list / recipe header | R228: 3. מתכון ייצור ופעולות (Master | S228: A21 | T228: =HYPERLINK("#'"&R228&"'!"&S228,"➜ פתח")
N229: שדה | O229: PLNTY | P229: סוג רשימה | Q229: Task list type (2=recipe) | R229: 3. מתכון ייצור ופעולות (Master | S229: C22 | T229: =HYPERLINK("#'"&R229&"'!"&S229,"➜ פתח")
N230: שדה | O230: PLNNR | P230: קבוצת רשימת פעולות | Q230: Key for task list group | R230: 3. מתכון ייצור ופעולות (Master | S230: C23 | T230: =HYPERLINK("#'"&R230&"'!"&S230,"➜ פתח")
N231: שדה | O231: PLNAL | P231: מונה קבוצה / חלופה | Q231: Group counter | R231: 3. מתכון ייצור ופעולות (Master | S231: C24 | T231: =HYPERLINK("#'"&R231&"'!"&S231,"➜ פתח")
N232: שדה | O232: VERWE | P232: שימוש | Q232: Task list usage | R232: 3. מתכון ייצור ופעולות (Master | S232: C25 | T232: =HYPERLINK("#'"&R232&"'!"&S232,"➜ פתח")
N233: שדה | O233: STATU | P233: סטטוס | Q233: Task list status | R233: 3. מתכון ייצור ופעולות (Master | S233: C26 | T233: =HYPERLINK("#'"&R233&"'!"&S233,"➜ פתח")
N234: שדה | O234: LOSVN | P234: גודל אצווה מ | Q234: Lot size from | R234: 3. מתכון ייצור ופעולות (Master | S234: C27 | T234: =HYPERLINK("#'"&R234&"'!"&S234,"➜ פתח")
N235: שדה | O235: LOSBS | P235: גודל אצווה עד | Q235: Lot size to | R235: 3. מתכון ייצור ופעולות (Master | S235: C28 | T235: =HYPERLINK("#'"&R235&"'!"&S235,"➜ פתח")
N236: טרנזקציה | O236: C201 | P236: כותרת מתכון ייצור / רשימת פעולות | Q236: Task list / recipe header | R236: 3. מתכון ייצור ופעולות (Master | S236: A22 | T236: =HYPERLINK("#'"&R236&"'!"&S236,"➜ פתח")
N237: טרנזקציה | O237: C202 | P237: כותרת מתכון ייצור / רשימת פעולות | Q237: Task list / recipe header | R237: 3. מתכון ייצור ופעולות (Master | S237: A22 | T237: =HYPERLINK("#'"&R237&"'!"&S237,"➜ פתח")
N238: טרנזקציה | O238: C203 | P238: כותרת מתכון ייצור / רשימת פעולות | Q238: Task list / recipe header | R238: 3. מתכון ייצור ופעולות (Master | S238: A22 | T238: =HYPERLINK("#'"&R238&"'!"&S238,"➜ פתח")
N239: טבלה | O239: PLPO | P239: פעולות/פאזות במתכון | Q239: Task list - operation / activity | R239: 3. מתכון ייצור ופעולות (Master | S239: A30 | T239: =HYPERLINK("#'"&R239&"'!"&S239,"➜ פתח")
... N310: טרנזקציה | O310: C223 | P310: Manage Production Versions | Q310: F2703 | R310: 4. גרסאות ייצור (Production Ver | S310: A6 | T310: =HYPERLINK("#'"&R310&"'!"&S310,"➜ פתח")
...

Sheet 1. נתוני אב חומר ויחידות מידה (
A1: ◄ חזרה למסך הראשי | C1: 1. נתוני אב חומר ויחידות מידה (Material & UoM) | ECC 6.0 ➜ S/4HANA · CBC NEO
A2: מס' (#) | B2: טבלה (Table) | C2: שדה טכני (Field) | D2: סוג נתונים (Type) | E2: אורך (Len) | F2: מפתח (Key) | G2: English Term | H2: תרגום עברי (Hebrew) | I2: JOIN ON (SQL / CDS) | J2: הסבר פונקציונלי בעברית | K2: פער / הערת S/4HANA | L2: SAP Help
A3: 🔧 שכבה תפעולית (Operational Layer) - T-codes ◄► Fiori | ממשקים BAPI/IDoc/RFC | תוכניות רקע ודוחות
A4: מיפוי T-code ◄► Fiori App (ECC ◄► S/4HANA)
A5: ECC T-code | D5: S/4HANA Fiori App | I5: Fiori ID
A6: MM01 / MM02 / MM03 | D6: Manage Product Master Data | I6: F1602A
A7: MM50 (extend views) | D7: Manage Product Master Data | I7: F1602A
A8: MMSC (ext. storage loc.) | D8: Mass Maintenance - Products | I8: -
A9: CUNI (UoM config) | D9: Configure Units of Measure (SPRO) | I9: -
A10: ממשקים ובלוקים פונקציונליים: BAPIs / IDocs / RFCs (Extraction & Messaging)
A11: Type | C11: Name | G11: תיאור / Description
A12: BAPI | C12: BAPI_MATERIAL_SAVEDATA | G12: יצירה/עדכון אב חומר - ליבת הטעינה ההמונית והממשקים
A13: BAPI | C13: BAPI_MATERIAL_GET_DETAIL | G13: שליפת נתוני חומר לדוחות/ממשקים
A14: IDoc | C14: MATMAS (MATMAS05) | G14: הפצת אב חומר ל/מ-מערכות חיצוניות (Zetes/Daymax)
A15: RFC | C15: MARA_SINGLE_READ / MARC_SINGLE_READ | G15: קריאת חומר/מפעל בודד
A16: תוכניות רקע ודוחות סטנדרטיים (Background Programs / Reports)
A17: Program / Report | E17: תיאור ומטרה / Usage & Trigger
A18: RMMG2000 | E18: טעינה/עדכון חומר המוני (Direct Input)
A19: RMDATIND | E19: Direct Input לאב חומר מממשק
A20: RMMM00B0 / MM60 | E20: דוח רשימת חומרים
A22: ◆ טבלה MARA - נתוני אב חומר כלליים (General material data) | T-codes: MM01/MM02/MM03; MM50, MMSC
A23: 1 | B23: MARA | C23: MATNR | D23: CHAR | E23: 18->40 | F23: PK | G23: Material number | H23: מספר חומר | I23: (header - root of material model) | J23: טבלת הליבה של כל חומר ב-CBC (חומרי גלם, תרכיזים, חומרי אריזה, מוצרים מוגמרים). מפתח MATNR מורחב מ-18 ל-40 תווים ב-S/4HANA - קריטי לממשקי IDoc ל-Zetes/Daymax ולברקודים. כל פעולת ייצור (COR1/COR2) נשענת על רשומת חומר תקינה. | K23: MATNR מורחב 18->40 (SAP Note 2267140); בדוק ממשקים, ברקודים והמרות EAN. | L23: SAP Help - Material Master
A24: 2 | C24: MTART | D24: CHAR | E24: 4 | F24: FK | G24: Material type | H24: סוג חומר
A25: 3 | C25: MEINS | D25: UNIT | E25: 3 | F25: FK | G25: Base unit of measure | H25: יחידת מידה בסיסית
A26: 4 | C26: MATKL | D26: CHAR | E26: 9 | F26: FK | G26: Material group | H26: קבוצת חומר
A27: 5 | C27: GROES | D27: CHAR | E27: 32 | F27: - | G27: Size / dimensions | H27: גודל / מידות
A28: 6 | C28: BRGEW | D28: QUAN | E28: 13 | F28: - | G28: Gross weight | H28: משקל ברוטו
A29: 7 | C29: NTGEW | D29: QUAN | E29: 13 | F29: - | G29: Net weight | H29: משקל נטו
A30: 8 | C30: XCHPF | D30: CHAR | E30: 1 | F30: - | G30: Batch management indicator | H30: ניהול אצוות
A32: ◆ טבלה MAKT - תיאורי חומר (טקסטים) (Material descriptions) | T-codes: MM01/MM02/MM03
A33: 9 | B33: MAKT | C33: MATNR | D33: CHAR | E33: 18->40 | F33: PK/FK | G33: Material number | H33: מספר חומר | I33: FROM MAKT JOIN MARA ON MAKT.MATNR = MARA.MATNR | J33: תיאורי החומר הרב-לשוניים (עברית/אנגלית) המוצגים בפק"ע, בתעודות ובממשקי הלוגיסטיקה. חיוני לתצוגה דו-לשונית במסופי Zetes. | K33: ללא שינוי; MATNR מורחב משפיע על המפתח. | L33: SAP Help - Material Master
A34: 10 | C34: SPRAS | D34: LANG | E34: 1 | F34: PK | G34: Language key | H34: שפה
A35: 11 | C35: MAKTX | D35: CHAR | E35: 40 | F35: - | G35: Material description | H35: תיאור חומר
A36: 12 | C36: MAKTG | D36: CHAR | E36: 40 | F36: - | G36: Description (upper case) | H36: תיאור (אותיות גדולות)
A38: ◆ טבלה MARC - נתוני חומר ברמת מפעל (Plant data for material) | T-codes: MM01/MM02; MD04, CO09
A39: 13 | B39: MARC | C39: MATNR | D39: CHAR | E39: 18->40 | F39: PK/FK | G39: Material number | H39: מספר חומר | I39: FROM MARC JOIN MARA ON MARC.MATNR = MARA.MATNR | J39: פרמטרי התכנון והייצור של החומר במפעל CBC הספציפי: סוג רכש, MRP, אופק תכנון, גרסת ייצור ברירת מחדל. שדה SBDKZ/SFCPF שולט בזרימת הייצור (Process Order). | K39: MRP Live מחליף MRP קלאסי; שדות תכנון נשמרים אך הביצוע ב-MATDOC/ACDOCA. | L39: SAP Help - Plant Data
A40: 14 | C40: WERKS | D40: CHAR | E40: 4 | F40: PK | G40: Plant | H40: מפעל
A41: 15 | C41: DISPO | D41: CHAR | E41: 3 | F41: FK | G41: MRP controller | H41: אחראי MRP
A42: 16 | C42: DISMM | D42: CHAR | E42: 2 | F42: - | G42: MRP type | H42: סוג MRP
A43: 17 | C43: BESKZ | D43: CHAR | E43: 1 | F43: - | G43: Procurement type | H43: סוג רכש
A44: 18 | C44: SOBSL | D44: CHAR | E44: 2 | F44: - | G44: Special procurement | H44: רכש מיוחד
A45: 19 | C45: FEVOR | D45: CHAR | E45: 3 | F45: FK | G45: Production scheduler | H45: מתזמן ייצור
A46: 20 | C46: SERNP | D46: CHAR | E46: 4 | F46: - | G46: Serial number profile | H46: פרופיל מספר סידורי
A48: ◆ טבלה MARD - נתוני חומר ברמת מחסן/מלאי (Storage location / stock data) | T-codes: MMBE; MB52
A49: 21 | B49: MARD | C49: MATNR | D49: CHAR | E49: 18->40 | F49: PK/FK | G49: Material number | H49: מספר חומר | I49: FROM MARD JOIN MARC ON MARD.MATNR = MARC.MATNR AND MARD.WERKS = MARC.WERKS | J49: מלאי החומר לפי מחסן במפעל. בסיס לפליטת חומרי גלם לפק"ע ולקליטת מוצר מוגמר; מסונכרן עם מסופי Zetes/Daymax בזמן אמת. | K49: מלאי מנוהל ב-MATDOC; MARD הופך ל-Aggregate/View. | L49: SAP Help - Inventory
A50: 22 | C50: WERKS | D50: CHAR | E50: 4 | F50: PK/FK | G50: Plant | H50: מפעל
A51: 23 | C51: LGORT | D51: CHAR | E51: 4 | F51: PK | G51: Storage location | H51: מחסן
A52: 24 | C52: LABST | D52: QUAN | E52: 13 | F52: - | G52: Unrestricted stock | H52: מלאי פנוי
A53: 25 | C53: INSME | D53: QUAN | E53: 13 | F53: - | G53: Stock in quality inspection | H53: מלאי בבדיקת איכות
A55: ◆ טבלה MARM - המרות יחידות מידה חלופיות (Units of measure conversions) | T-codes: MM02 (תצוגת UoM)
A56: 26 | B56: MARM | C56: MATNR | D56: CHAR | E56: 18->40 | F56: PK/FK | G56: Material number | H56: מספר חומר | I56: FROM MARM JOIN MARA ON MARM.MATNR = MARA.MATNR | J56: מקדמי המרה בין יחידות (UMREZ מונה / UMREN מכנה) - לדוגמה ארגז=24 בקבוקים, משטח=ארגזים. קריטי לבקרת פחת ייצור של 1%: עיגול שגוי במקדם גורם לסטיית מלאי. EAN11 לברקוד. | K56: ללא שינוי מבני; אמת מקדמי עיגול (rounding) למניעת סטיות מלאי. | L56: SAP Help - Units of Measure
A57: 27 | C57: MEINH | D57: UNIT | E57: 3 | F57: PK | G57: Alternative unit of measure | H57: יחידת מידה חלופית
A58: 28 | C58: UMREZ | D58: DEC | E58: 5 | F58: - | G58: Numerator for conversion | H58: מונה להמרה
A59: 29 | C59: UMREN | D59: DEC | E59: 5 | F59: - | G59: Denominator for conversion | H59: מכנה להמרה
A60: 30 | C60: EAN11 | D60: CHAR | E60: 18 | F60: - | G60: International article number (EAN/UPC) | H60: ברקוד בינלאומי
A61: 31 | C61: MESUB | D61: UNIT | E61: 3 | F61: - | G61: Lowest level UoM | H61: יחידה ברמה הנמוכה
A63: ◆ טבלה MEAN - ברקודים / EAN לחומר (International article numbers (EANs)) | T-codes: MM02
A64: 32 | B64: MEAN | C64: MATNR | D64: CHAR | E64: 18->40 | F64: PK/FK | G64: Material number | H64: מספר חומר | I64: FROM MEAN JOIN MARA ON MEAN.MATNR = MARA.MATNR | J64: ניהול ברקודים מרובים לחומר (EAN13, UPC, GTIN) לפי יחידת מידה. מקור הסריקה במסופי Zetes בקליטה ובמשלוח. | K64: ללא שינוי. | L64: SAP Help - EAN
A65: 33 | C65: MEINH | D65: UNIT | E65: 3 | F65: PK | G65: Unit of measure | H65: יחידת מידה
A66: 34 | C66: EAN11 | D66: CHAR | E66: 18 | F66: PK | G66: EAN / barcode | H66: ברקוד EAN
A67: 35 | C67: EANTP | D67: CHAR | E67: 2 | F67: - | G67: EAN category | H67: סוג EAN
A68: 36 | C68: HPEAN | D68: CHAR | E68: 1 | F68: - | G68: Main EAN indicator | H68: ברקוד ראשי
A70: ◆ טבלה MBEW - הערכת חומר (Valuation) (Material valuation) | T-codes: MM02; MR21, CKM3
A71: 37 | B71: MBEW | C71: MATNR | D71: CHAR | E71: 18->40 | F71: PK/FK | G71: Material number | H71: מספר חומר | I71: FROM MBEW JOIN MARA ON MBEW.MATNR = MARA.MATNR | J71: מחיר התקן/ממוצע נע של החומר לתמחיר ייצור והתחשבנות פק"ע. ב-CBC משמש לחישוב עלות תרכיז/מוצר מוגמר. | K71: Material Ledger חובה ב-S/4HANA; הערכה ב-ACDOCA/ACDOCC. | L71: SAP Note - Material Ledger
A72: 38 | C72: BWKEY | D72: CHAR | E72: 4 | F72: PK | G72: Valuation area | H72: אזור הערכה
A73: 39 | C73: BWTAR | D73: CHAR | E73: 10 | F73: PK | G73: Valuation type | H73: סוג הערכה
A74: 40 | C74: VPRSV | D74: CHAR | E74: 1 | F74: - | G74: Price control (S/V) | H74: בקרת מחיר
A75: 41 | C75: STPRS | D75: CURR | E75: 11 | F75: - | G75: Standard price | H75: מחיר תקן
A76: 42 | C76: PEINH | D76: DEC | E76: 5 | F76: - | G76: Price unit | H76: יחידת מחיר
A78: ◆ טבלה MVKE - נתוני חומר ברמת מכירות (Sales data for material) | T-codes: MM01/MM02
A79: 43 | B79: MVKE | C79: MATNR | D79: CHAR | E79: 18->40 | F79: PK/FK | G79: Material number | H79: מספר חומר | I79: FROM MVKE JOIN MARA ON MVKE.MATNR = MARA.MATNR | J79: נתוני מכירה של מוצר מוגמר (ארגון מכירות, ערוץ הפצה) - מחבר את הייצור לשרשרת ההפצה של CBC. | K79: ללא שינוי; לקוחות דרך Business Partner. | L79: SAP Help - Sales Data
A80: 44 | C80: VKORG | D80: CHAR | E80: 4 | F80: PK | G80: Sales organization | H80: ארגון מכירות
A81: 45 | C81: VTWEG | D81: CHAR | E81: 2 | F81: PK | G81: Distribution channel | H81: ערוץ הפצה
A82: 46 | C82: MTPOS | D82: CHAR | E82: 4 | F82: - | G82: Item category group | H82: קבוצת קטגוריית פריט
A84: ◆ טבלה MLAN - נתוני מס לחומר (לפי מדינה) (Material tax data) | T-codes: MM01/MM02
A85: 47 | B85: MLAN | C85: MATNR | D85: CHAR | E85: 18->40 | F85: PK/FK | G85: Material number | H85: מספר חומר | I85: FROM MLAN JOIN MARA ON MLAN.MATNR = MARA.MATNR | J85: סיווג מס (מע"מ/בלו) לחומר לפי מדינה - רלוונטי למשקאות החייבים בבלו/מס בריאות בישראל. | K85: ללא שינוי. | L85: SAP Help - Tax Classification
A86: 48 | C86: ALAND | D86: CHAR | E86: 3 | F86: PK | G86: Departure country | H86: מדינת מקור
A87: 49 | C87: TAXM1 | D87: CHAR | E87: 1 | F87: - | G87: Tax classification | H87: סיווג מס
A89: ◆ טבלה MLGN - נתוני חומר ברמת מחסן (WM) (Material data for warehouse number) | T-codes: MM01/MM02
A90: 50 | B90: MLGN | C90: MATNR | D90: CHAR | E90: 18->40 | F90: PK/FK | G90: Material number | H90: מספר חומר | I90: FROM MLGN JOIN MARA ON MLGN.MATNR = MARA.MATNR | J90: פרמטרי ניהול מחסן (WM/EWM) של החומר - יחידת בסיס לאחסון, אסטרטגיית העלאה/הורדה. ממשק למסופי Zetes. | K90: EWM אסטרטגי; LE-WM קלאסי נתמך עם הגבלות. | L90: SAP Help - Warehouse
A91: 51 | C91: LGNUM | D91: CHAR | E91: 3 | F91: PK | G91: Warehouse number | H91: מספר מחסן
A92: 52 | C92: LTKZA | D92: CHAR | E92: 3 | F92: - | G92: Stock removal strategy | H92: אסטרטגיית הורדה
A93: 53 | C93: LTKZE | D93: CHAR | E93: 3 | F93: - | G93: Stock placement strategy | H93: אסטרטגיית העלאה
A95: ◆ טבלה MLGT - נתוני חומר לפי טיפוס אחסון (Material data for storage type) | T-codes: MM01/MM02
A96: 54 | B96: MLGT | C96: MATNR | D96: CHAR | E96: 18->40 | F96: PK/FK | G96: Material number | H96: מספר חומר | I96: FROM MLGT JOIN MLGN ON MLGT.MATNR = MLGN.MATNR AND MLGT.LGNUM = MLGN.LGNUM | J96: כמויות/אזורי אחסון לפי טיפוס במחסן - בקרת מיקום אצווה במחסן הקירור/יבש. | K96: EWM אסטרטגי. | L96: SAP Help - Storage Type
A97: 55 | C97: LGNUM | D97: CHAR | E97: 3 | F97: PK/FK | G97: Warehouse number | H97: מספר מחסן
A98: 56 | C98: LGTYP | D98: CHAR | E98: 3 | F98: PK | G98: Storage type | H98: טיפוס אחסון
A99: 57 | C99: LPMAX | D99: QUAN | E99: 13 | F99: - | G99: Maximum bin quantity | H99: כמות תא מקסימלית
A101: ◆ טבלה MDMA - אזורי MRP לחומר (MRP areas for material) | T-codes: MM02; MDLV
A102: 58 | B102: MDMA | C102: MATNR | D102: CHAR | E102: 18->40 | F102: PK/FK | G102: Material number | H102: מספר חומר | I102: FROM MDMA JOIN MARC ON MDMA.MATNR = MARC.MATNR AND MDMA.WERKS = MARC.WERKS | J102: הפרדת תכנון לאזורי MRP (קו ייצור/מחסן) בתוך המפעל - מאפשר תכנון נפרד לקו בקבוק מול קו פחית. | K102: אזורי MRP פעילים כברירת מחדל ב-MRP Live. | L102: SAP Help - MRP Areas
A103: 59 | C103: WERKS | D103: CHAR | E103: 4 | F103: PK/FK | G103: Plant | H103: מפעל
A104: 60 | C104: BERID | D104: CHAR | E104: 10 | F104: PK | G104: MRP area | H104: אזור MRP
A105: 61 | C105: DISMM | D105: CHAR | E105: 2 | F105: - | G105: MRP type | H105: סוג MRP
A107: ◆ טבלה QMAT - הגדרות בדיקת איכות לחומר (Inspection setup data for material) | T-codes: QA08; MM02
A108: 62 | B108: QMAT | C108: MATNR | D108: CHAR | E108: 18->40 | F108: PK/FK | G108: Material number | H108: מספר חומר | I108: FROM QMAT JOIN MARC ON QMAT.MATNR = MARC.MATNR AND QMAT.WERKS = MARC.WERKS | J108: הפעלת סוגי בדיקה (קליטה/ייצור/שחרור) לחומר - מחבר את הייצור ל-QM. קריטי לשחרור אצווה לפני משלוח. | K108: ללא שינוי מבני. | L108: SAP Help - Quality Inspection
A109: 63 | C109: WERKS | D109: CHAR | E109: 4 | F109: PK/FK | G109: Plant | H109: מפעל
A110: 64 | C110: ART | D110: CHAR | E110: 8 | F110: PK | G110: Inspection type | H110: סוג בדיקה
A111: 65 | C111: AKTIV | D111: CHAR | E111: 1 | F111: - | G111: Active indicator | H111: פעיל
A113: ◆ טבלה MCH1 - אצוות חומר (Batches) (Batch master records) | T-codes: MSC1N/MSC2N/MSC3N
A114: 66 | B114: MCH1 | C114: MATNR | D114: CHAR | E114: 18->40 | F114: PK/FK | G114: Material number | H114: מספר חומר | I114: FROM MCH1 JOIN MARA ON MCH1.MATNR = MARA.MATNR | J114: רשומות האצווה של החומר - קריטי במשקאות לניהול תאריך תפוגה (VFDAT/BBD), תאריך ייצור ומעקב גנאלוגיה (Track & Trace). כל פליטה/קליטה בקו מנוהלת לפי אצווה ומסונכרנת עם Zetes. | K114: ללא שינוי מבני; MATNR מורחב 18->40 במפתח. | L114: SAP Help - Batch Management
...

Sheet 2. עץ מוצר (BOM)
A1: ◄ חזרה למסך הראשי | C1: 2. עץ מוצר (BOM) | ECC 6.0 ➜ S/4HANA · CBC NEO
A2: מס' (#) | B2: טבלה (Table) | C2: שדה טכני (Field) | D2: סוג נתונים (Type) | E2: אורך (Len) | F2: מפתח (Key) | G2: English Term | H2: תרגום עברי (Hebrew) | I2: JOIN ON (SQL / CDS) | J2: הסבר פונקציונלי בעברית | K2: פער / הערת S/4HANA | L2: SAP Help
A3: 🔧 שכבה תפעולית (Operational Layer) - T-codes ◄► Fiori | ממשקים BAPI/IDoc/RFC | תוכניות רקע ודוחות
A4: מיפוי T-code ◄► Fiori App (ECC ◄► S/4HANA)
A5: ECC T-code | D5: S/4HANA Fiori App | I5: Fiori ID
A6: CS01 / CS02 / CS03 | D6: Maintain Bill of Material | I6: F1743
A7: CS11 / CS12 / CS15 | D7: Manage Material BOMs | I7: F1813
A8: CEWB (eng. workbench) | D8: Manage Bill of Materials | I8: F1813
A9: ממשקים ובלוקים פונקציונליים: BAPIs / IDocs / RFCs (Extraction & Messaging)
A10: Type | C10: Name | G10: תיאור / Description
A11: BAPI | C11: BAPI_MATERIAL_BOM_GROUP_CREATE | G11: יצירת עץ מוצר (S/4 BOM API)
A12: FM | C12: CSAP_MAT_BOM_MAINTAIN | G12: תחזוקת עץ מוצר (ECC)
A13: IDoc | C13: BOMMAT | G13: הפצת עץ מוצר חומר בין מערכות
A14: RFC | C14: CS_BOM_EXPL_MAT_RC1 | G14: פיצוץ עץ מוצר לחומר
A15: תוכניות רקע ודוחות סטנדרטיים (Background Programs / Reports)
A16: Program / Report | E16: תיאור ומטרה / Usage & Trigger
A17: RCSBOM00 | E17: עיבוד/בדיקת עצי מוצר המוני
A18: RCSBI010 | E18: פיצוץ עץ מוצר רב-רמתי
A19: CS_BT | E19: דוח Where-Used לרכיב
A21: ◆ טבלה MAST - קישור חומר לעץ מוצר (Material to BOM link) | T-codes: CS01/CS02/CS03
A22: 1 | B22: MAST | C22: MATNR | D22: CHAR | E22: 18->40 | F22: PK/FK | G22: Material number | H22: מספר חומר | I22: FROM MAST JOIN MARA ON MAST.MATNR = MARA.MATNR | J22: מקשר בין חומר/מפעל לבין עץ המוצר (Recipe BOM). מפתח ההצטרפות לכל פיצוץ רכיבים בפק"ע. עץ מוצר = 'עץ מוצר' / Bill of Material. | K22: ללא שינוי; MATNR מורחב משפיע על המפתח ועל IDNRK. | L22: SAP Help - Bill of Material
A23: 2 | C23: WERKS | D23: CHAR | E23: 4 | F23: PK | G23: Plant | H23: מפעל
A24: 3 | C24: STLAN | D24: CHAR | E24: 1 | F24: PK | G24: BOM usage (1=Production) | H24: שימוש עץ מוצר
A25: 4 | C25: STLNR | D25: CHAR | E25: 8 | F25: FK | G25: Bill of material number | H25: מספר עץ מוצר
A26: 5 | C26: STLAL | D26: CHAR | E26: 2 | F26: PK | G26: Alternative BOM | H26: חלופת עץ מוצר
A28: ◆ טבלה STKO - כותרת עץ מוצר (BOM header) | T-codes: CS01/CS02/CS03
A29: 6 | B29: STKO | C29: STLTY | D29: CHAR | E29: 1 | F29: PK | G29: BOM category | H29: קטגוריית עץ מוצר | I29: FROM STKO JOIN MAST ON STKO.STLNR = MAST.STLNR | J29: כותרת עץ המוצר: כמות בסיס, יחידה, סטטוס ותוקף. כמות הבסיס (BMENG) קובעת את יחס הרכיבים - קריטי לדיוק מתכון/פחת. | K29: ללא שינוי. | L29: SAP Help - BOM Header
A30: 7 | C30: STLNR | D30: CHAR | E30: 8 | F30: PK | G30: Bill of material number | H30: מספר עץ מוצר
A31: 8 | C31: STLAL | D31: CHAR | E31: 2 | F31: PK | G31: Alternative BOM | H31: חלופת עץ מוצר
A32: 9 | C32: BMENG | D32: QUAN | E32: 13 | F32: - | G32: Base quantity | H32: כמות בסיס
A33: 10 | C33: BMEIN | D33: UNIT | E33: 3 | F33: FK | G33: Base unit of measure | H33: יחידת בסיס
A34: 11 | C34: STLST | D34: NUMC | E34: 2 | F34: - | G34: BOM status | H34: סטטוס עץ מוצר
A36: ◆ טבלה STPO - פריטי עץ מוצר (רכיבים) (BOM item) | T-codes: CS02; CS11, CS15
A37: 12 | B37: STPO | C37: STLTY | D37: CHAR | E37: 1 | F37: PK/FK | G37: BOM category | H37: קטגוריית עץ מוצר | I37: FROM STPO JOIN STKO ON STPO.STLNR = STKO.STLNR AND STPO.STLTY = STKO.STLTY | J37: רכיבי עץ המוצר: כל חומר גלם/אריזה, כמותו (MENGE) וסוג הפריט. כאן מוגדר פחת רכיב (AUSCH %) לבקרת 1% פחת ייצור. | K37: ללא שינוי; IDNRK מורחב 18->40. | L37: SAP Help - BOM Item
A38: 13 | C38: STLNR | D38: CHAR | E38: 8 | F38: PK/FK | G38: Bill of material number | H38: מספר עץ מוצר
A39: 14 | C39: STLKN | D39: NUMC | E39: 8 | F39: PK | G39: BOM item node number | H39: מספר צומת פריט
A40: 15 | C40: POSNR | D40: CHAR | E40: 4 | F40: - | G40: BOM item number | H40: מספר פריט
A41: 16 | C41: IDNRK | D41: CHAR | E41: 18->40 | F41: FK | G41: Component (BOM item material) | H41: רכיב / חומר
A42: 17 | C42: MENGE | D42: QUAN | E42: 13 | F42: - | G42: Component quantity | H42: כמות רכיב
A43: 18 | C43: MEINS | D43: UNIT | E43: 3 | F43: FK | G43: Component unit | H43: יחידת רכיב
A44: 19 | C44: AUSCH | D44: DEC | E44: 6 | F44: - | G44: Component scrap (%) | H44: פחת רכיב (%)
A45: 20 | C45: POSTP | D45: CHAR | E45: 1 | F45: - | G45: Item category | H45: סוג פריט
A47: ◆ טבלה STAS - בחירת פריטי עץ מוצר (BOM item selection) | T-codes: CS02 (CC)
A48: 21 | B48: STAS | C48: STLTY | D48: CHAR | E48: 1 | F48: PK/FK | G48: BOM category | H48: קטגוריית עץ מוצר | I48: FROM STAS JOIN STKO ON STAS.STLNR = STKO.STLNR | J48: מקשר בין פריטי STPO לחלופה/שינוי ההנדסי (ECM). שולט אילו רכיבים תקפים לתאריך נתון. | K48: ללא שינוי. | L48: SAP Help - BOM Variants
A49: 22 | C49: STLNR | D49: CHAR | E49: 8 | F49: PK/FK | G49: Bill of material number | H49: מספר עץ מוצר
A50: 23 | C50: STLAL | D50: CHAR | E50: 2 | F50: PK | G50: Alternative BOM | H50: חלופה
A51: 24 | C51: STLKN | D51: NUMC | E51: 8 | F51: FK | G51: Item node number | H51: מספר צומת
A52: 25 | C52: STASZ | D52: NUMC | E52: 8 | F52: PK | G52: Internal counter | H52: מונה פנימי
A54: ◆ טבלה STZU - טבלת היסטוריה/קישור לעץ מוצר (BOM history / link table) | T-codes: CS80 (CC overview)
A55: 26 | B55: STZU | C55: STLTY | D55: CHAR | E55: 1 | F55: PK/FK | G55: BOM category | H55: קטגוריית עץ מוצר | I55: FROM STZU JOIN STKO ON STZU.STLNR = STKO.STLNR | J55: מנהל את היסטוריית השינויים וקישורי ה-ECM של עץ המוצר - חיוני למעקב גרסאות מתכון לאורך זמן. | K55: ללא שינוי. | L55: SAP Help - Engineering Change
A56: 27 | C56: STLNR | D56: CHAR | E56: 8 | F56: PK/FK | G56: Bill of material number | H56: מספר עץ מוצר
A57: 28 | C57: STLAN | D57: CHAR | E57: 1 | F57: - | G57: BOM usage | H57: שימוש
A58: 29 | C58: AENNR | D58: CHAR | E58: 12 | F58: FK | G58: Change number (ECM) | H58: מספר שינוי הנדסי
A60: ◆ טבלה STPU - טקסטים ארוכים לפריט עץ מוצר (BOM sub-items / texts) | T-codes: CS02
A61: 30 | B61: STPU | C61: STLKN | D61: NUMC | E61: 8 | F61: PK/FK | G61: Item node number | H61: מספר צומת פריט | I61: FROM STPU JOIN STPO ON STPU.STLKN = STPO.STLKN | J61: תת-פריטים/כמויות נקודתיות של רכיב בעץ המוצר (לדוגמה כמות לפי מיקום התקנה). | K61: ללא שינוי. | L61: SAP Help - BOM Sub-items
A62: 31 | C62: SUMNR | D62: NUMC | E62: 4 | F62: PK | G62: Sub-item number | H62: מספר תת-פריט
A63: 32 | C63: MENGE | D63: QUAN | E63: 13 | F63: - | G63: Sub-item quantity | H63: כמות תת-פריט
A65: ◆ טבלה KDST - שימוש עץ מוצר בהזמנת לקוח (BOM explosion (sales order)) | T-codes: CS61
A66: 33 | B66: KDST | C66: VBELN | D66: CHAR | E66: 10 | F66: PK | G66: Sales document | H66: מסמך מכירה | I66: FROM KDST JOIN MAST ON KDST.MATNR = MAST.MATNR | J66: מקשר עצי מוצר ספציפיים להזמנת לקוח (Make-to-Order) - רלוונטי לייצור מבצעים/מותגים פרטיים. | K66: ללא שינוי. | L66: SAP Help - Sales Order BOM
A67: 34 | C67: POSNR | D67: NUMC | E67: 6 | F67: PK | G67: Sales document item | H67: פריט מסמך מכירה
A68: 35 | C68: MATNR | D68: CHAR | E68: 18->40 | F68: FK | G68: Material number | H68: מספר חומר
A69: 36 | C69: STLNR | D69: CHAR | E69: 8 | F69: FK | G69: BOM number | H69: מספר עץ מוצר

Sheet 3. מתכון ייצור ופעולות (Master 
A1: ◄ חזרה למסך הראשי | C1: 3. מתכון ייצור ופעולות (Master Recipe) | ECC 6.0 ➜ S/4HANA · CBC NEO
A2: מס' (#) | B2: טבלה (Table) | C2: שדה טכני (Field) | D2: סוג נתונים (Type) | E2: אורך (Len) | F2: מפתח (Key) | G2: English Term | H2: תרגום עברי (Hebrew) | I2: JOIN ON (SQL / CDS) | J2: הסבר פונקציונלי בעברית | K2: פער / הערת S/4HANA | L2: SAP Help
A3: 🔧 שכבה תפעולית (Operational Layer) - T-codes ◄► Fiori | ממשקים BAPI/IDoc/RFC | תוכניות רקע ודוחות
A4: מיפוי T-code ◄► Fiori App (ECC ◄► S/4HANA)
A5: ECC T-code | D5: S/4HANA Fiori App | I5: Fiori ID
A6: C201 / C202 / C203 | D6: Manage Master Recipes | I6: -
A7: C251 (print) | D7: Master Recipe Print | I7: -
A8: COIO (production cockpit) | D8: Process Order Information System | I8: -
A9: ממשקים ובלוקים פונקציונליים: BAPIs / IDocs / RFCs (Extraction & Messaging)
A10: Type | C10: Name | G10: תיאור / Description
A11: RFC | C11: CP_RECIPE_READ | G11: קריאת מתכון ייצור
A12: BAPI | C12: BAPI_CENTRAL_CHARACT_CREATE | G12: יצירת מאפיין בדיקה ראשי (QM)
A13: IDoc | C13: LOIPRO | G13: הוראות ייצור - מהמתכון לפק"ע ולקו
A14: PI | C14: Control Recipe / PI Sheet (PI Messages) | G14: שליחת הוראות תהליך לבקר/MES (Zetes/Daymax)
A15: תוכניות רקע ודוחות סטנדרטיים (Background Programs / Reports)
A16: Program / Report | E16: תיאור ומטרה / Usage & Trigger
A17: RCEXMASS | E17: עיבוד המוני מתכונים
A18: RCPRECIPE | E18: דוח/הערכת מתכונים
A19: RCO_CONTROL_RECIPE | E19: יצירת/שליחת Control Recipe
A21: ◆ טבלה PLKO - כותרת מתכון ייצור / רשימת פעולות (Task list / recipe header) | T-codes: C201/C202/C203
A22: 1 | B22: PLKO | C22: PLNTY | D22: CHAR | E22: 1 | F22: PK | G22: Task list type (2=recipe) | H22: סוג רשימה | I22: FROM PLKO JOIN MAPL ON PLKO.PLNTY = MAPL.PLNTY AND PLKO.PLNNR = MAPL.PLNNR | J22: כותרת מתכון הייצור (Master Recipe, PLNTY='2'). מגדיר אצווה תקנית, סטטוס ושימוש. 'מתכון ייצור' = Master Recipe. ב-CBC כל משקה מיוצר לפי מתכון מאושר. | K22: ללא שינוי מבני; Fiori 'Manage Master Recipes'. | L22: SAP Help - Master Recipe
A23: 2 | C23: PLNNR | D23: CHAR | E23: 8 | F23: PK | G23: Key for task list group | H23: קבוצת רשימת פעולות
A24: 3 | C24: PLNAL | D24: CHAR | E24: 2 | F24: PK | G24: Group counter | H24: מונה קבוצה / חלופה
A25: 4 | C25: VERWE | D25: CHAR | E25: 3 | F25: FK | G25: Task list usage | H25: שימוש
A26: 5 | C26: STATU | D26: CHAR | E26: 2 | F26: - | G26: Task list status | H26: סטטוס
A27: 6 | C27: LOSVN | D27: QUAN | E27: 13 | F27: - | G27: Lot size from | H27: גודל אצווה מ
A28: 7 | C28: LOSBS | D28: QUAN | E28: 13 | F28: - | G28: Lot size to | H28: גודל אצווה עד
A30: ◆ טבלה PLPO - פעולות/פאזות במתכון (Task list - operation / activity) | T-codes: C202
A31: 8 | B31: PLPO | C31: PLNTY | D31: CHAR | E31: 1 | F31: PK/FK | G31: Task list type | H31: סוג רשימה | I31: FROM PLPO JOIN PLAS ON PLPO.PLNTY = PLAS.PLNTY AND PLPO.PLNNR = PLAS.PLNNR AND PLPO.PLNKN = PLAS.PLNKN | J31: פעולות ופאזות הייצור (ערבוב, פסטור, מילוי). מפתח בקרה (STEUS) קובע אם הפעולה פנימית/קבלן, ומפעיל הוראות תהליך (Process Instructions) ל-PI sheet ולבקרים. ARBPL=משאב. | K31: ללא שינוי; ביצוע דרך Control Recipe / PI sheet. | L31: SAP Help - Recipe Operations
A32: 9 | C32: PLNNR | D32: CHAR | E32: 8 | F32: PK/FK | G32: Task list group | H32: קבוצת רשימה
A33: 10 | C33: PLNKN | D33: NUMC | E33: 8 | F33: PK | G33: Node number (operation) | H33: מספר צומת פעולה
A34: 11 | C34: VORNR | D34: CHAR | E34: 4 | F34: - | G34: Operation number | H34: מספר פעולה
A35: 12 | C35: ARBID | D35: NUMC | E35: 8 | F35: FK | G35: Work center / resource (object id) | H35: משאב (מזהה אובייקט)
A36: 13 | C36: STEUS | D36: CHAR | E36: 4 | F36: FK | G36: Control key | H36: מפתח בקרה
A37: 14 | C37: LTXA1 | D37: CHAR | E37: 40 | F37: - | G37: Operation short text | H37: תיאור פעולה
A38: 15 | C38: VGW01 | D38: QUAN | E38: 9 | F38: - | G38: Standard value 1 (setup) | H38: ערך תקן 1 (הקמה)
A39: 16 | C39: VGW02 | D39: QUAN | E39: 9 | F39: - | G39: Standard value 2 (machine) | H39: ערך תקן 2 (מכונה)
A41: ◆ טבלה PLAS - שיוך/בחירת פעולות לרשימה (Task list - operation selection) | T-codes: C202
A42: 17 | B42: PLAS | C42: PLNTY | D42: CHAR | E42: 1 | F42: PK/FK | G42: Task list type | H42: סוג רשימה | I42: FROM PLAS JOIN PLKO ON PLAS.PLNTY = PLKO.PLNTY AND PLAS.PLNNR = PLKO.PLNNR | J42: מקשר פעולות (PLPO) לכותרת ולרצף, ושולט בתוקף לפי שינוי הנדסי. שכבת הבחירה של הפעולות התקפות. | K42: ללא שינוי. | L42: SAP Help - Operation Selection
A43: 18 | C43: PLNNR | D43: CHAR | E43: 8 | F43: PK/FK | G43: Task list group | H43: קבוצת רשימה
A44: 19 | C44: PLNAL | D44: CHAR | E44: 2 | F44: PK | G44: Group counter | H44: מונה קבוצה
A45: 20 | C45: PLNKN | D45: NUMC | E45: 8 | F45: PK | G45: Node number | H45: מספר צומת
A46: 21 | C46: ZAEHL | D46: NUMC | E46: 8 | F46: PK | G46: Internal counter | H46: מונה פנימי
A47: 22 | C47: LOEKZ | D47: CHAR | E47: 1 | F47: - | G47: Deletion indicator | H47: מחוון מחיקה
A49: ◆ טבלה PLFL - רצפים במתכון (Task list - sequences) | T-codes: C202
A50: 23 | B50: PLFL | C50: PLNTY | D50: CHAR | E50: 1 | F50: PK/FK | G50: Task list type | H50: סוג רשימה | I50: FROM PLFL JOIN PLKO ON PLFL.PLNNR = PLKO.PLNNR | J50: מגדיר רצפי פעולות (סטנדרטי/מקביל/חלופי) - מאפשר ייצור מקבילי בקווי בקבוק/פחית. | K50: ללא שינוי. | L50: SAP Help - Sequences
A51: 24 | C51: PLNNR | D51: CHAR | E51: 8 | F51: PK/FK | G51: Task list group | H51: קבוצת רשימה
A52: 25 | C52: PLNFL | D52: CHAR | E52: 6 | F52: PK | G52: Sequence number | H52: מספר רצף
A53: 26 | C53: FLGAT | D53: CHAR | E53: 1 | F53: - | G53: Sequence category | H53: קטגוריית רצף
A55: ◆ טבלה PLMZ - שיוך רכיבים לפעולות (Component allocation (BOM to operation)) | T-codes: C202 (Comp. Alloc.)
A56: 27 | B56: PLMZ | C56: PLNTY | D56: CHAR | E56: 1 | F56: PK/FK | G56: Task list type | H56: סוג רשימה | I56: FROM PLMZ JOIN PLPO ON PLMZ.PLNKN = PLPO.PLNKN | J56: מקשר רכיבי עץ מוצר (STPO) לפעולות במתכון - קובע באיזו פאזה נצרך כל חומר גלם. בסיס לפליטת חומרים מדורגת בפק"ע. | K56: ללא שינוי. | L56: SAP Help - Component Allocation
A57: 28 | C57: PLNNR | D57: CHAR | E57: 8 | F57: PK/FK | G57: Task list group | H57: קבוצת רשימה
A58: 29 | C58: ZUONR | D58: NUMC | E58: 8 | F58: PK | G58: Allocation node | H58: צומת שיוך
A59: 30 | C59: PLNKN | D59: NUMC | E59: 8 | F59: FK | G59: Operation node | H59: צומת פעולה
A60: 31 | C60: STLKN | D60: NUMC | E60: 8 | F60: FK | G60: BOM item node | H60: צומת פריט עץ מוצר
A62: ◆ טבלה PLMK - מאפייני בדיקה במתכון (Inspection characteristics) | T-codes: C202; QP01
A63: 32 | B63: PLMK | C63: PLNTY | D63: CHAR | E63: 1 | F63: PK/FK | G63: Task list type | H63: סוג רשימה | I63: FROM PLMK JOIN PLPO ON PLMK.PLNKN = PLPO.PLNKN | J63: מאפייני בדיקת איכות המשובצים בפעולות המתכון (Brix, pH, CO2, טמפ'). מפעיל מסמכי בדיקה אוטומטיים בפק"ע - לב בקרת האיכות של CBC. | K63: ללא שינוי מבני. | L63: SAP Help - Inspection Characteristics
A64: 33 | C64: PLNNR | D64: CHAR | E64: 8 | F64: PK/FK | G64: Task list group | H64: קבוצת רשימה
A65: 34 | C65: MERKNR | D65: NUMC | E65: 4 | F65: PK | G65: Inspection characteristic number | H65: מספר מאפיין בדיקה
A66: 35 | C66: PLNKN | D66: NUMC | E66: 8 | F66: FK | G66: Operation node | H66: צומת פעולה
A67: 36 | C67: VERWMERKM | D67: CHAR | E67: 8 | F67: FK | G67: Master inspection characteristic | H67: מאפיין בדיקה ראשי
A68: 37 | C68: SOLLWERT | D68: CHAR | E68: 18 | F68: - | G68: Target value | H68: ערך יעד
A70: ◆ טבלה MAPL - שיוך חומר למתכון/רשימת פעולות (Material to task list assignment) | T-codes: C201/C202
A71: 38 | B71: MAPL | C71: MATNR | D71: CHAR | E71: 18->40 | F71: PK/FK | G71: Material number | H71: מספר חומר | I71: FROM MAPL JOIN MARC ON MAPL.MATNR = MARC.MATNR AND MAPL.WERKS = MARC.WERKS | J71: מקשר בין חומר (מוצר) למתכון הייצור שלו במפעל. נקודת ההצטרפות שגרסת הייצור (MKAL) מצביעה אליה. | K71: ללא שינוי. | L71: SAP Help - Material Assignment
A72: 39 | C72: WERKS | D72: CHAR | E72: 4 | F72: PK | G72: Plant | H72: מפעל
A73: 40 | C73: PLNTY | D73: CHAR | E73: 1 | F73: FK | G73: Task list type | H73: סוג רשימה
A74: 41 | C74: PLNNR | D74: CHAR | E74: 8 | F74: FK | G74: Task list group | H74: קבוצת רשימה
A75: 42 | C75: PLNAL | D75: CHAR | E75: 2 | F75: FK | G75: Group counter | H75: מונה קבוצה
A77: ◆ טבלה FHMI - שיוך כלי עזר ייצור (PRT) לפעולה (Production resources/tools allocation) | T-codes: C202 (PRT)
A78: 43 | B78: FHMI | C78: PLNTY | D78: CHAR | E78: 1 | F78: PK/FK | G78: Task list type | H78: סוג רשימה | I78: FROM FHMI JOIN PLPO ON FHMI.PLNKN = PLPO.PLNKN | J78: מקשר כלי עזר ייצור (תבניות, מסננים, פורמטים) לפעולות המתכון - מעקב כיול וזמינות PRT. | K78: ללא שינוי. | L78: SAP Help - PRT
A79: 44 | C79: PLNNR | D79: CHAR | E79: 8 | F79: PK/FK | G79: Task list group | H79: קבוצת רשימה
A80: 45 | C80: PLNKN | D80: NUMC | E80: 8 | F80: FK | G80: Operation node | H80: צומת פעולה
A81: 46 | C81: FHMNR | D81: CHAR | E81: 18 | F81: FK | G81: PRT (resource/tool) | H81: כלי עזר ייצור
A83: ◆ טבלה PLZU - קישור היסטוריית רשימת פעולות (Task list link / history) | T-codes: C202
A84: 47 | B84: PLZU | C84: PLNTY | D84: CHAR | E84: 1 | F84: PK/FK | G84: Task list type | H84: סוג רשימה | I84: FROM PLZU JOIN PLKO ON PLZU.PLNNR = PLKO.PLNNR | J84: מנהל גרסאות ושינויים הנדסיים של רשימת הפעולות/המתכון - מעקב אחר עדכוני מתכון מאושרים. | K84: ללא שינוי. | L84: SAP Help - Task List Change
A85: 48 | C85: PLNNR | D85: CHAR | E85: 8 | F85: PK/FK | G85: Task list group | H85: קבוצת רשימה
A86: 49 | C86: AENNR | D86: CHAR | E86: 12 | F86: FK | G86: Change number | H86: מספר שינוי
A88: ◆ טבלה TC60 - מאפייני הוראות תהליך (PI) (Process instruction characteristics) | T-codes: O09C; SPRO
A89: 50 | B89: TC60 | C89: STEUS | D89: CHAR | E89: 4 | F89: PK | G89: Control key | H89: מפתח בקרה | I89: FROM PLPO JOIN TC60 ON PLPO.STEUS = TC60.STEUS | J89: מגדיר את מאפייני הוראות התהליך (Process Instructions) שנשלחים לבקר/PI sheet בעת שחרור פק"ע - לב ה-PP-PI מול אוטומציית הקו. | K89: ללא שינוי (Customizing). | L89: SAP Help - Process Instructions
A90: 51 | C90: PVZNR | D90: NUMC | E90: 4 | F90: PK | G90: PI characteristic number | H90: מספר מאפיין PI
A91: 52 | C91: ATNAM | D91: CHAR | E91: 30 | F91: FK | G91: Characteristic name | H91: שם מאפיין
A93: ◆ טבלה TCA01 - פרופיל רשימת פעולות (Customizing) (Task list profile) | T-codes: SPRO
A94: 53 | B94: TCA01 | C94: PROFIDNETZ | D94: CHAR | E94: 7 | F94: PK | G94: Profile ID | H94: מזהה פרופיל | I94: FROM PLKO JOIN TCA01 ON PLKO.PROFIDNETZ = TCA01.PROFIDNETZ | J94: פרופיל ברירת מחדל לרשימות פעולות/מתכונים (ערכי ברירת מחדל למפתחות בקרה, יחידות). מאיץ תחזוקת מתכונים אחידה. | K94: ללא שינוי (Customizing). | L94: SAP Help - Task List Profile
A95: 54 | C95: PLNTY | D95: CHAR | E95: 1 | F95: FK | G95: Task list type | H95: סוג רשימה
A96: 55 | C96: STEUS | D96: CHAR | E96: 4 | F96: FK | G96: Default control key | H96: מפתח בקרה ברירת מחדל

Sheet 4. גרסאות ייצור (Production Ver
A1: ◄ חזרה למסך הראשי | C1: 4. גרסאות ייצור (Production Versions - חובה ב-S/4) | ECC 6.0 ➜ S/4HANA · CBC NEO
A2: מס' (#) | B2: טבלה (Table) | C2: שדה טכני (Field) | D2: סוג נתונים (Type) | E2: אורך (Len) | F2: מפתח (Key) | G2: English Term | H2: תרגום עברי (Hebrew) | I2: JOIN ON (SQL / CDS) | J2: הסבר פונקציונלי בעברית | K2: פער / הערת S/4HANA | L2: SAP Help
A3: 🔧 שכבה תפעולית (Operational Layer) - T-codes ◄► Fiori | ממשקים BAPI/IDoc/RFC | תוכניות רקע ודוחות
A4: מיפוי T-code ◄► Fiori App (ECC ◄► S/4HANA)
A5: ECC T-code | D5: S/4HANA Fiori App | I5: Fiori ID
A6: C223 | D6: Manage Production Versions | I6: F2703
A7: MM02 (PV tab) | D7: Manage Product Master Data | I7: F1602A
A8: CC01/CC02 (ECM) | D8: Manage Change Records | I8: -
A9: ממשקים ובלוקים פונקציונליים: BAPIs / IDocs / RFCs (Extraction & Messaging)
A10: Type | C10: Name | G10: תיאור / Description
A11: BAPI | C11: BAPI_MATERIAL_SAVEDATA (PVERSIONS) | G11: יצירה/עדכון גרסת ייצור
A12: BAPI | C12: BAPI_PRODVERS_CREATE_REPLACE | G12: יצירה/החלפת גרסת ייצור (אמת)
A13: FM | C13: CM_FV_PROD_VERS_READ | G13: קריאת גרסאות ייצור לחומר/מפעל
A14: תוכניות רקע ודוחות סטנדרטיים (Background Programs / Reports)
A15: Program / Report | E15: תיאור ומטרה / Usage & Trigger
A16: RCC22300 / RSC22300 | E16: בדיקת עקביות המונית של גרסאות ייצור (Pre-check ל-S/4)
A17: CS_BD_DIRECT_LINK | E17: יצירת קישור ישיר BOM<->Recipe לגרסה
A19: ◆ טבלה MKAL - גרסאות ייצור לחומר (Production versions for materials) | T-codes: C223; MM02 (PV)
A20: 1 | B20: MKAL | C20: MATNR | D20: CHAR | E20: 18->40 | F20: PK/FK | G20: Material number | H20: מספר חומר | I20: FROM MKAL JOIN MARC ON MKAL.MATNR = MARC.MATNR AND MKAL.WERKS = MARC.WERKS | J20: 'גרסת ייצור' (Production Version) מקשרת חומר -> עץ מוצר (STLAL) + מתכון (PLNNR) + קו ייצור. ב-S/4HANA היא חובה מוחלטת (100%) לכל ביצוע ייצור - מחליפה את לוגיקת בחירת BOM/Routing האוטומטית של ECC. ב-CBC כל שילוב מוצר/קו = גרסה. ללא PV תקפה הפק"ע (COR1) לא תיווצר. | K20: חובה 100% ב-S/4HANA - הרץ C223 ובדוק תוקף/עקביות לכל חומר מיוצר לפני ההמרה (Pre-check קריטי). | L20: SAP Note - Production Versions Mandatory
A21: 2 | C21: WERKS | D21: CHAR | E21: 4 | F21: PK/FK | G21: Plant | H21: מפעל
A22: 3 | C22: VERID | D22: CHAR | E22: 4 | F22: PK | G22: Production version | H22: מזהה גרסת ייצור
A23: 4 | C23: TEXT1 | D23: CHAR | E23: 40 | F23: - | G23: Production version text | H23: תיאור גרסת ייצור
A24: 5 | C24: ADATU | D24: DATS | E24: 8 | F24: - | G24: Valid-from date | H24: תקף מ
A25: 6 | C25: BDATU | D25: DATS | E25: 8 | F25: - | G25: Valid-to date | H25: תקף עד
A26: 7 | C26: BSTMI | D26: QUAN | E26: 13 | F26: - | G26: Lot size from | H26: גודל אצווה מ
A27: 8 | C27: BSTMA | D27: QUAN | E27: 13 | F27: - | G27: Lot size to | H27: גודל אצווה עד
A28: 9 | C28: STLAL | D28: CHAR | E28: 2 | F28: FK | G28: Alternative BOM | H28: חלופת עץ מוצר
A29: 10 | C29: STLAN | D29: CHAR | E29: 1 | F29: FK | G29: BOM usage | H29: שימוש עץ מוצר
A30: 11 | C30: PLNTY | D30: CHAR | E30: 1 | F30: FK | G30: Task list type (recipe) | H30: סוג רשימה
A31: 12 | C31: PLNNR | D31: CHAR | E31: 8 | F31: FK | G31: Task list group (recipe) | H31: קבוצת מתכון
A32: 13 | C32: ALNAL | D32: CHAR | E32: 2 | F32: FK | G32: Task list group counter | H32: מונה רשימה
... A34: 15 | C34: PRFG_NEW | D34: CHAR | E34: 1 | F34: - | G34: Detailed PV check status | H34: סטטוס בדיקת תקינות

Sheet 5. משאבים  מרכזי עבודה (Resourc
A1: ◄ חזרה למסך הראשי | C1: 5. משאבים / מרכזי עבודה (Resources) | ECC 6.0 ➜ S/4HANA · CBC NEO
A2: מס' (#) | B2: טבלה (Table) | C2: שדה טכני (Field) | D2: סוג נתונים (Type) | E2: אורך (Len) | F2: מפתח (Key) | G2: English Term | H2: תרגום עברי (Hebrew) | I2: JOIN ON (SQL / CDS) | J2: הסבר פונקציונלי בעברית | K2: פער / הערת S/4HANA | L2: SAP Help
A3: 🔧 שכבה תפעולית (Operational Layer) - T-codes ◄► Fiori | ממשקים BAPI/IDoc/RFC | תוכניות רקע ודוחות
A4: מיפוי T-code ◄► Fiori App (ECC ◄► S/4HANA)
A5: ECC T-code | D5: S/4HANA Fiori App | I5: Fiori ID
A6: CRC1 / CRC2 / CRC3 | D6: Manage Work Centers / Resources | I6: F3794
A7: CR11 / CR12 / CR13 | D7: Manage Capacity | I7: -
A8: KP26 (activity rates) | D8: Manage Cost Rates | I8: -
A9: ממשקים ובלוקים פונקציונליים: BAPIs / IDocs / RFCs (Extraction & Messaging)
A10: Type | C10: Name | G10: תיאור / Description
A11: RFC | C11: CR_WORK_CENTER_READ | G11: קריאת נתוני מרכז עבודה/משאב
A12: FM | C12: CRAP_WORKCENTER_GET_DETAIL | G12: שליפת פרטי משאב
A13: FM | C13: CY_CAPACITY_LOAD | G13: חישוב עומס קיבולת
A14: תוכניות רקע ודוחות סטנדרטיים (Background Programs / Reports)
A15: Program / Report | E15: תיאור ומטרה / Usage & Trigger
A16: RCCRSE00 / CR05 | E16: דוח מרכזי עבודה/משאבים
A17: RIABC000 | E17: ניתוח קיבולת / ABC (אמת)
A18: RCCYPL00 / CM01 | E18: הערכת עומסי קיבולת
A20: ◆ טבלה CRHD - כותרת משאב / מרכז עבודה (Work center / resource header) | T-codes: CRC1/CRC2/CRC3; CR01
A21: 1 | B21: CRHD | C21: OBJTY | D21: CHAR | E21: 2 | F21: PK | G21: Object type (A=work center) | H21: סוג אובייקט | I21: (header - root of resource model) | J21: המשאב (קו מילוי, ערבל, פסטרייזר) שעליו מתבצעות פעולות המתכון. OBJTY='A'. מקושר לקיבולת ולמרכז עלות. ב-CBC כל קו ייצור = משאב עם קיבולת מתוזמנת. | K21: ללא שינוי מבני; Fiori 'Manage Work Centers'. | L21: SAP Help - Work Center
A22: 2 | C22: OBJID | D22: NUMC | E22: 8 | F22: PK | G22: Object ID | H22: מזהה אובייקט
A23: 3 | C23: ARBPL | D23: CHAR | E23: 8 | F23: - | G23: Work center / resource code | H23: קוד משאב
A24: 4 | C24: WERKS | D24: CHAR | E24: 4 | F24: FK | G24: Plant | H24: מפעל
A25: 5 | C25: VERWE | D25: CHAR | E25: 4 | F25: FK | G25: Usage | H25: שימוש
A26: 6 | C26: VERAN | D26: CHAR | E26: 3 | F26: - | G26: Person responsible | H26: אחראי
A27: 7 | C27: PLANV | D27: CHAR | E27: 3 | F27: - | G27: Capacity planner group | H27: קבוצת מתכנן קיבולת
A29: ◆ טבלה CRTX - טקסטים של משאב (Work center / resource texts) | T-codes: CRC2/CRC3
A30: 8 | B30: CRTX | C30: OBJTY | D30: CHAR | E30: 2 | F30: PK/FK | G30: Object type | H30: סוג אובייקט | I30: FROM CRTX JOIN CRHD ON CRTX.OBJID = CRHD.OBJID AND CRTX.OBJTY = CRHD.OBJTY | J30: תיאורי המשאב הרב-לשוניים המוצגים בפעולות ובלוח התזמון. | K30: ללא שינוי. | L30: SAP Help - Work Center
A31: 9 | C31: OBJID | D31: NUMC | E31: 8 | F31: PK/FK | G31: Object ID | H31: מזהה אובייקט
A32: 10 | C32: SPRAS | D32: LANG | E32: 1 | F32: PK | G32: Language key | H32: שפה
A33: 11 | C33: KTEXT | D33: CHAR | E33: 40 | F33: - | G33: Description | H33: תיאור
A35: ◆ טבלה CRCO - שיוך משאב למרכז עלות (Work center to cost center assignment) | T-codes: CRC2 (Costing)
A36: 12 | B36: CRCO | C36: OBJTY | D36: CHAR | E36: 2 | F36: PK/FK | G36: Object type | H36: סוג אובייקט | I36: FROM CRCO JOIN CRHD ON CRCO.OBJID = CRHD.OBJID AND CRCO.OBJTY = CRHD.OBJTY | J36: מקשר את המשאב למרכז עלות ולסוגי פעילות (Activity Types) - בסיס לתמחיר שעות מכונה/עבודה בפק"ע ולהתחשבנות ב-ACDOCA. | K36: התחשבנות ב-Universal Journal (ACDOCA); הקצאה נשמרת. | L36: SAP Help - Work Center Costing
A37: 13 | C37: OBJID | D37: NUMC | E37: 8 | F37: PK/FK | G37: Object ID | H37: מזהה אובייקט
A38: 14 | C38: LANUM | D38: NUMC | E38: 3 | F38: PK | G38: Sequence number | H38: מספר רצף
A39: 15 | C39: KOKRS | D39: CHAR | E39: 4 | F39: FK | G39: Controlling area | H39: אזור בקרה
A40: 16 | C40: KOSTL | D40: CHAR | E40: 10 | F40: FK | G40: Cost center | H40: מרכז עלות
A41: 17 | C41: LSTAR | D41: CHAR | E41: 6 | F41: FK | G41: Activity type | H41: סוג פעילות
A43: ◆ טבלה CRCA - הקצאת קיבולת למשאב (Work center capacity allocation) | T-codes: CR11/CR12; CRC2
A44: 18 | B44: CRCA | C44: OBJTY | D44: CHAR | E44: 2 | F44: PK/FK | G44: Object type | H44: סוג אובייקט | I44: FROM CRCA JOIN CRHD ON CRCA.OBJID = CRHD.OBJID AND CRCA.OBJTY = CRHD.OBJTY | J44: מקשר את המשאב לקיבולת (KAKO) - שעות זמינות ביום/משמרת. בסיס לתכנון עומסים ולתזמון פק"ע בקו. | K44: ללא שינוי. | L44: SAP Help - Capacity
A45: 19 | C45: OBJID | D45: NUMC | E45: 8 | F45: PK/FK | G45: Object ID | H45: מזהה אובייקט
A46: 20 | C46: CAPID | D46: CHAR | E46: 3 | F46: PK | G46: Capacity category | H46: קטגוריית קיבולת
A47: 21 | C47: KAPID | D47: NUMC | E47: 8 | F47: FK | G47: Capacity ID | H47: מזהה קיבולת
A49: ◆ טבלה KAKO - כותרת קיבולת (Capacity header) | T-codes: CR11/CR12/CR13
A50: 22 | B50: KAKO | C50: KAPID | D50: NUMC | E50: 8 | F50: PK | G50: Capacity ID | H50: מזהה קיבולת | I50: FROM KAKO JOIN CRCA ON KAKO.KAPID = CRCA.KAPID | J50: מגדיר את הקיבולת עצמה: לוח משמרות, ניצולת (%), מספר יחידות. קובע את הזמינות בפועל של קו הייצור. | K50: ללא שינוי. | L50: SAP Help - Capacity Header
A51: 23 | C51: KAPAR | D51: CHAR | E51: 3 | F51: - | G51: Capacity category | H51: קטגוריית קיבולת
A52: 24 | C52: AZNOR | D52: DEC | E52: 3 | F52: - | G52: Number of individual capacities | H52: מספר יחידות קיבולת
A53: 25 | C53: NGRAD | D53: DEC | E53: 3 | F53: - | G53: Capacity utilization (%) | H53: ניצולת קיבולת
A55: ◆ טבלה CRFH - אב כלי עזר ייצור (PRT) (Production resource/tool master) | T-codes: CF01/CF02/CF03
A56: 26 | B56: CRFH | C56: OBJTY | D56: CHAR | E56: 2 | F56: PK | G56: Object type (F=PRT) | H56: סוג אובייקט | I56: FROM FHMI JOIN CRFH ON FHMI.FHMNR = CRFH.FHMNR | J56: רשומת אב של כלי עזר ייצור (PRT) - תבניות מילוי, פורמטים, מסננים. כולל נתוני כיול וזמינות לשיבוץ במתכון. | K56: ללא שינוי. | L56: SAP Help - PRT Master
A57: 27 | C57: OBJID | D57: NUMC | E57: 8 | F57: PK | G57: Object ID | H57: מזהה אובייקט
A58: 28 | C58: FHMNR | D58: CHAR | E58: 18 | F58: - | G58: PRT number | H58: מספר כלי עזר
A59: 29 | C59: FHMART | D59: CHAR | E59: 1 | F59: - | G59: PRT category | H59: קטגוריית כלי עזר
A61: ◆ טבלה CRVD_A - ברירות מחדל למשאב (PI) (Resource default values) | T-codes: CRC2
A62: 30 | B62: CRVD_A | C62: OBJTY | D62: CHAR | E62: 2 | F62: PK/FK | G62: Object type | H62: סוג אובייקט | I62: FROM CRVD_A JOIN CRHD ON CRVD_A.OBJID = CRHD.OBJID | J62: ערכי ברירת מחדל ספציפיים למשאב PI (מפתח בקרה, סוג פעילות) - מאיצים תחזוקת מתכונים אחידה בקו. | K62: ללא שינוי. | L62: SAP Help - Resource Defaults
A63: 31 | C63: OBJID | D63: NUMC | E63: 8 | F63: PK/FK | G63: Object ID | H63: מזהה אובייקט
A64: 32 | C64: STEUS | D64: CHAR | E64: 4 | F64: FK | G64: Default control key | H64: מפתח בקרה
A66: ◆ טבלה CSLA - סוגי פעילות למרכז עבודה (Activity types for work center) | T-codes: KP26; CRC2
A67: 33 | B67: CSLA | C67: LSTAR | D67: CHAR | E67: 6 | F67: PK | G67: Activity type | H67: סוג פעילות | I67: FROM CSLA JOIN CRCO ON CSLA.LSTAR = CRCO.LSTAR | J67: מגדיר את סוגי הפעילות (שעת מכונה, שעת אדם, אנרגיה) ותעריפיהם - בסיס לתמחיר עלות ייצור משתנה ב-CBC. | K67: תעריפים ב-Universal Journal; הגדרה נשמרת. | L67: SAP Help - Activity Types
A68: 34 | C68: KOKRS | D68: CHAR | E68: 4 | F68: PK | G68: Controlling area | H68: אזור בקרה
A69: 35 | C69: LEINH | D69: UNIT | E69: 3 | F69: - | G69: Activity unit | H69: יחידת פעילות
A71: ◆ טבלה KAZT - מרווחי קיבולת זמינה (Capacity available intervals) | T-codes: CR11/CR12/CR13
A72: 36 | B72: KAZT | C72: KAPID | D72: NUMC | E72: 8 | F72: PK/FK | G72: Capacity ID | H72: מזהה קיבולת | I72: FROM KAZT JOIN KAKO ON KAZT.KAPID = KAKO.KAPID | J72: מגדיר את הקיבולת הזמינה בפועל לאורך זמן (לפי משמרת/יום/מרווח) - שעות המכונה הזמינות לתזמון פק"ע בקו. בסיס לתכנון עומסים מדויק (CM01) ולזיהוי צווארי בקבוק. | K72: ללא שינוי מבני. | L72: SAP Help - Available Capacity
A73: 37 | C73: VERSN | D73: NUMC | E73: 3 | F73: PK | G73: Capacity version | H73: גרסת קיבולת
A74: 38 | C74: TPROG | D74: CHAR | E74: 2 | F74: - | G74: Shift sequence / grouping | H74: רצף משמרות
A75: 39 | C75: BEGZT | D75: TIMS | E75: 6 | F75: - | G75: Start time | H75: שעת התחלה
A76: 40 | C76: ENDZT | D76: TIMS | E76: 6 | F76: - | G76: End time | H76: שעת סיום
A77: 41 | C77: KAPAZ | D77: DEC | E77: 11 | F77: - | G77: Available capacity | H77: קיבולת זמינה

Sheet 6. פק"ע ייצור ומתכון בקרה (Proc
A1: ◄ חזרה למסך הראשי | C1: 6. פק"ע ייצור ומתכון בקרה (Process Order) | ECC 6.0 ➜ S/4HANA · CBC NEO
A2: מס' (#) | B2: טבלה (Table) | C2: שדה טכני (Field) | D2: סוג נתונים (Type) | E2: אורך (Len) | F2: מפתח (Key) | G2: English Term | H2: תרגום עברי (Hebrew) | I2: JOIN ON (SQL / CDS) | J2: הסבר פונקציונלי בעברית | K2: פער / הערת S/4HANA | L2: SAP Help
A3: 🔧 שכבה תפעולית (Operational Layer) - T-codes ◄► Fiori | ממשקים BAPI/IDoc/RFC | תוכניות רקע ודוחות
A4: מיפוי T-code ◄► Fiori App (ECC ◄► S/4HANA)
A5: ECC T-code | D5: S/4HANA Fiori App | I5: Fiori ID
A6: COR1 / COR2 / COR3 | D6: Create / Change / Display Process Order | I6: -
A7: COR6N (confirm) | D7: Confirm Production Operation | I7: F3372
A8: COIO / COOIS | D8: Process Order Information System | I8: -
A9: COHV (mass proc.) | D9: Mass Processing - Orders | I9: -
A10: ממשקים ובלוקים פונקציונליים: BAPIs / IDocs / RFCs (Extraction & Messaging)
A11: Type | C11: Name | G11: תיאור / Description
A12: BAPI | C12: BAPI_PROCORD_CREATE / _RELEASE | G12: יצירה/שחרור פק"ע ייצור
A13: BAPI | C13: BAPI_PROCORDCONF_CREATE_TT | G13: דיווח ביצוע פק"ע (Time Ticket)
A14: IDoc | C14: LOIPRO | G14: שליחת פק"ע/הוראות ייצור ל-MES (Zetes/Daymax)
A15: IDoc | C15: PPCC1 (PP-PI message) | G15: הודעות תהליך/דיווח מהקו חזרה ל-SAP
A16: תוכניות רקע ודוחות סטנדרטיים (Background Programs / Reports)
A17: Program / Report | E17: תיאור ומטרה / Usage & Trigger
A18: MD01 / MD01N (MRP Live) | E18: הרצת MRP - תכנון חומרים וייצור
A19: COHV / RCO_BATCH_SCHEDULE | E19: עיבוד המוני ותזמון אצוות פק"ע
A20: CO41 / CO48 (convert) | E20: המרת פק"ע מתוכננת לפק"ע ייצור
A22: ◆ טבלה AUFK - נתוני אב של פקודת ייצור (Order master data) | T-codes: COR1/COR2/COR3; COOIS
A23: 1 | B23: AUFK | C23: AUFNR | D23: CHAR | E23: 12 | F23: PK | G23: Order number | H23: מספר פק"ע | I23: (header - process order master) | J23: כותרת פק"ע הייצור (Process Order). נוצרת מגרסת ייצור (MKAL) + מתכון. שחרור הפק"ע מייצר Control Recipe ושולח הוראות תהליך לקו דרך IDoc. מעקב ב-COR2/COIO. | K23: מודל מותאם; עלויות ב-ACDOCA. | L23: SAP Help - Process Order
A24: 2 | C24: AUART | D24: CHAR | E24: 4 | F24: FK | G24: Order type | H24: סוג פק"ע
A25: 3 | C25: WERKS | D25: CHAR | E25: 4 | F25: FK | G25: Plant | H25: מפעל
A26: 4 | C26: OBJNR | D26: CHAR | E26: 22 | F26: FK | G26: Object number (status) | H26: מפתח אובייקט
A27: 5 | C27: KTEXT | D27: CHAR | E27: 40 | F27: - | G27: Description | H27: תיאור
A29: ◆ טבלה AFKO - כותרת פקודת ייצור (Order header data) | T-codes: COR2
A30: 6 | B30: AFKO | C30: AUFNR | D30: CHAR | E30: 12 | F30: PK/FK | G30: Order number | H30: מספר פק"ע | I30: FROM AFKO JOIN AUFK ON AFKO.AUFNR = AUFK.AUFNR | J30: נתוני הייצור של הפק"ע: כמות, מועדים, גרסת ייצור (VERID), מתכון. AUFPL מקשר לפעולות. בסיס לתזמון ולפליטת חומרים. | K30: מותאם (תואם). | L30: SAP Help - Order Header
A31: 7 | C31: GAMNG | D31: QUAN | E31: 13 | F31: - | G31: Total order quantity | H31: כמות פק"ע
A32: 8 | C32: GMEIN | D32: UNIT | E32: 3 | F32: FK | G32: Unit of measure | H32: יחידת מידה
A33: 9 | C33: VERID | D33: CHAR | E33: 4 | F33: FK | G33: Production version | H33: גרסת ייצור
A34: 10 | C34: AUFPL | D34: NUMC | E34: 10 | F34: FK | G34: Routing number of operations | H34: מספר תוכנית פעולות
A35: 11 | C35: GLTRP | D35: DATS | E35: 8 | F35: - | G35: Basic finish date | H35: תאריך סיום בסיסי
A37: ◆ טבלה AFPO - פריט פקודת ייצור (Order item) | T-codes: COR3
A38: 12 | B38: AFPO | C38: AUFNR | D38: CHAR | E38: 12 | F38: PK/FK | G38: Order number | H38: מספר פק"ע | I38: FROM AFPO JOIN AFKO ON AFPO.AUFNR = AFKO.AUFNR | J38: פריט הפק"ע: החומר המיוצר, כמות, מחסן קליטה, אצווה. נקודת קליטת המוצר המוגמר למלאי. | K38: מותאם (תואם). | L38: SAP Help - Order Item
A39: 13 | C39: POSNR | D39: NUMC | E39: 6 | F39: PK | G39: Order item number | H39: מספר פריט
A40: 14 | C40: MATNR | D40: CHAR | E40: 18->40 | F40: FK | G40: Material produced | H40: חומר מיוצר
A41: 15 | C41: PSMNG | D41: QUAN | E41: 13 | F41: - | G41: Order item quantity | H41: כמות פריט
A42: 16 | C42: CHARG | D42: CHAR | E42: 10 | F42: - | G42: Batch | H42: אצווה
A44: ◆ טבלה AFVC - פעולות פקודת הייצור (Order operations) | T-codes: COR2
A45: 17 | B45: AFVC | C45: AUFPL | D45: NUMC | E45: 10 | F45: PK/FK | G45: Routing number of operations | H45: מספר תוכנית פעולות | I45: FROM AFVC JOIN AFKO ON AFVC.AUFPL = AFKO.AUFPL | J45: פעולות/פאזות הפק"ע (מועתקות מהמתכון). מפתח בקרה קובע דיווח/הוראות תהליך. בסיס לדיווח ביצוע (CORK) ולתמחיר. | K45: מותאם (תואם). | L45: SAP Help - Order Operations
A46: 18 | C46: APLZL | D46: NUMC | E46: 8 | F46: PK | G46: Internal counter | H46: מונה פנימי
A47: 19 | C47: VORNR | D47: CHAR | E47: 4 | F47: - | G47: Operation number | H47: מספר פעולה
A48: 20 | C48: ARBID | D48: NUMC | E48: 8 | F48: FK | G48: Resource (object id) | H48: משאב
A49: 21 | C49: STEUS | D49: CHAR | E49: 4 | F49: FK | G49: Control key | H49: מפתח בקרה
A50: 22 | C50: LTXA1 | D50: CHAR | E50: 40 | F50: - | G50: Operation text | H50: תיאור פעולה
A52: ◆ טבלה RESB - הזמנת רכיבים לפק"ע (Reservation / dependent requirements) | T-codes: COR2; CO09
A53: 23 | B53: RESB | C53: RSNUM | D53: NUMC | E53: 10 | F53: PK | G53: Reservation number | H53: מספר הזמנה | I53: FROM RESB JOIN AFKO ON RESB.AUFNR = AFKO.AUFNR | J53: הזמנות חומרי הגלם/האריזה לפק"ע (מפיצוץ עץ המוצר). כל פליטת חומר (261) מעדכנת RESB. סנכרון עם מסופי Zetes בפליטה. | K53: ללא שינוי; תנועת מלאי ב-MATDOC. | L53: SAP Help - Reservation
A54: 24 | C54: RSPOS | D54: NUMC | E54: 4 | F54: PK | G54: Reservation item | H54: פריט הזמנה
A55: 25 | C55: MATNR | D55: CHAR | E55: 18->40 | F55: FK | G55: Component | H55: רכיב
A56: 26 | C56: BDMNG | D56: QUAN | E56: 13 | F56: - | G56: Requirement quantity | H56: כמות נדרשת
A57: 27 | C57: ENMNG | D57: QUAN | E57: 13 | F57: - | G57: Quantity withdrawn | H57: כמות שנפלטה
A58: 28 | C58: AUFNR | D58: CHAR | E58: 12 | F58: FK | G58: Order number | H58: מספר פק"ע
A60: ◆ טבלה AFRU - דיווחי ביצוע פק"ע (Order confirmations) | T-codes: CORK; COR6
A61: 29 | B61: AFRU | C61: RUECK | D61: NUMC | E61: 10 | F61: PK | G61: Confirmation number | H61: מספר דיווח | I61: FROM AFRU JOIN AFKO ON AFRU.AUFNR = AFKO.AUFNR | J61: דיווחי הביצוע על פעולות הפק"ע: כמות שיוצרה, פחת, זמני מכונה/אדם. מקור הנתונים מהקו (PI sheet/MES) ובסיס לעלות ולניתוח פחת מול 1% היעד. | K61: ללא שינוי; עלויות ב-ACDOCA. | L61: SAP Help - Confirmation
A62: 30 | C62: RMZHL | D62: NUMC | E62: 8 | F62: PK | G62: Confirmation counter | H62: מונה דיווח
A63: 31 | C63: AUFNR | D63: CHAR | E63: 12 | F63: FK | G63: Order number | H63: מספר פק"ע
A64: 32 | C64: LMNGA | D64: QUAN | E64: 13 | F64: - | G64: Yield (confirmed qty) | H64: כמות שיוצרה
A65: 33 | C65: XMNGA | D65: QUAN | E65: 13 | F65: - | G65: Scrap quantity | H65: כמות פחת
A67: ◆ טבלה AFFH - שיוך PRT לפק"ע (PRT allocation in order) | T-codes: COR2 (PRT)
A68: 34 | B68: AFFH | C68: AUFPL | D68: NUMC | E68: 10 | F68: PK/FK | G68: Routing number | H68: מספר תוכנית פעולות | I68: FROM AFFH JOIN AFKO ON AFFH.AUFPL = AFKO.AUFPL | J68: כלי עזר הייצור (PRT) המשובצים לפק"ע - תבניות/פורמטים נדרשים בקו לאצווה הספציפית. | K68: ללא שינוי. | L68: SAP Help - PRT in Order
A69: 35 | C69: APLZL | D69: NUMC | E69: 8 | F69: PK | G69: Counter | H69: מונה
A70: 36 | C70: FHMNR | D70: CHAR | E70: 18 | F70: FK | G70: PRT number | H70: מספר כלי עזר
A72: ◆ טבלה AFFL - רצפי פעולות בפק"ע (Order sequences (work order)) | T-codes: COR2
A73: 37 | B73: AFFL | C73: AUFPL | D73: NUMC | E73: 10 | F73: PK/FK | G73: Routing number of operations | H73: מספר תוכנית פעולות | I73: FROM AFFL JOIN AFKO ON AFFL.AUFPL = AFKO.AUFPL | J73: רצפי הפעולות בפק"ע (סטנדרטי/מקביל) - מאפשר ביצוע פאזות במקביל בקו הייצור ובסיס לתזמון מדויק. | K73: מותאם (תואם). | L73: SAP Help - Order Sequences
A74: 38 | C74: APLFL | D74: CHAR | E74: 6 | F74: PK | G74: Sequence | H74: רצף
A75: 39 | C75: PLNFL | D75: CHAR | E75: 6 | F75: - | G75: Reference sequence | H75: רצף ייחוס
A76: 40 | C76: FLGAT | D76: CHAR | E76: 1 | F76: - | G76: Sequence category | H76: קטגוריית רצף

Sheet 7. קונפיגורציה (Customizing)
A1: ◄ חזרה למסך הראשי | C1: 7. קונפיגורציה (Customizing) | ECC 6.0 ➜ S/4HANA · CBC NEO
A2: מס' (#) | B2: טבלה (Table) | C2: שדה טכני (Field) | D2: סוג נתונים (Type) | E2: אורך (Len) | F2: מפתח (Key) | G2: English Term | H2: תרגום עברי (Hebrew) | I2: JOIN ON (SQL / CDS) | J2: הסבר פונקציונלי בעברית | K2: פער / הערת S/4HANA | L2: SAP Help
A3: 🔧 שכבה תפעולית (Operational Layer) - T-codes ◄► Fiori | ממשקים BAPI/IDoc/RFC | תוכניות רקע ודוחות
A4: מיפוי T-code ◄► Fiori App (ECC ◄► S/4HANA)
A5: ECC T-code | D5: S/4HANA Fiori App | I5: Fiori ID
A6: COR4 (order type) | D6: Configure Order Types (SPRO) | I6: -
A7: OPL8 (plant params) | D7: Order Type-Dependent Parameters | I7: -
A8: BS02 (status profile) | D8: Maintain Status Profile | I8: -
A9: BP (Business Partner) | D9: Manage Business Partner Master Data | I9: -
A10: ממשקים ובלוקים פונקציונליים: BAPIs / IDocs / RFCs (Extraction & Messaging)
A11: Type | C11: Name | G11: תיאור / Description
A12: IDoc | C12: LOIPRO | G12: פק"ע/הוראות ייצור ל-MES
A13: BAPI | C13: BAPI_BUPA_CREATE_FROM_DATA | G13: יצירת שותף עסקי (BP)
A14: FM | C14: CVI_VENDOR_TO_BP_CONVERT | G14: המרת ספק ל-BP (CVI)
A15: RFC | C15: STATUS_CHANGE_INTERN | G15: שינוי סטטוס פנימי
A16: תוכניות רקע ודוחות סטנדרטיים (Background Programs / Reports)
A17: Program / Report | E17: תיאור ומטרה / Usage & Trigger
A18: RBDMIDOC | E18: יצירת IDocs להפצה (MATMAS/LOIPRO)
A19: MDS_LOAD_COCKPIT | E19: סנכרון Customer/Vendor Integration ל-BP
A20: RHALTD00 / RCOZP | E20: עיבוד/בדיקת קונפיגורציה
A22: ◆ טבלה T134 - סוגי חומר (Customizing) (Material types) | T-codes: OMS2; SPRO
A23: 1 | B23: T134 | C23: MTART | D23: CHAR | E23: 4 | F23: PK | G23: Material type | H23: סוג חומר | I23: FROM MARA JOIN T134 ON MARA.MTART = T134.MTART | J23: מגדיר סוגי חומר (ROH גלם, FERT מוגמר, HALB ביניים, VERP אריזה) ושולט באילו תצוגות/שדות חובה. בסיס לסיווג כל חומרי CBC. | K23: ללא שינוי (Customizing). | L23: SAP Help - Material Types
A24: 2 | C24: MBRSH | D24: CHAR | E24: 1 | F24: - | G24: Industry sector | H24: ענף
A25: 3 | C25: KKREF | D25: CHAR | E25: 4 | F25: - | G25: Account category reference | H25: הפניית קטגוריית חשבון
A27: ◆ טבלה T134T - טקסטים לסוגי חומר (Material type descriptions) | T-codes: OMS2
A28: 4 | B28: T134T | C28: MTART | D28: CHAR | E28: 4 | F28: PK/FK | G28: Material type | H28: סוג חומר | I28: FROM T134T JOIN T134 ON T134T.MTART = T134.MTART | J28: תיאורי סוגי החומר הרב-לשוניים. | K28: ללא שינוי. | L28: SAP Help - Material Types
A29: 5 | C29: SPRAS | D29: LANG | E29: 1 | F29: PK | G29: Language key | H29: שפה
A30: 6 | C30: MTBEZ | D30: CHAR | E30: 25 | F30: - | G30: Material type description | H30: תיאור סוג חומר
A32: ◆ טבלה T023 - קבוצות חומר (Customizing) (Material groups) | T-codes: OMSF; SPRO
A33: 7 | B33: T023 | C33: MATKL | D33: CHAR | E33: 9 | F33: PK | G33: Material group | H33: קבוצת חומר | I33: FROM MARA JOIN T023 ON MARA.MATKL = T023.MATKL | J33: מגדיר קבוצות חומר לקיבוץ דיווחי וניתוח רכש/ייצור - לדוגמה 'תרכיזים', 'בקבוקי PET', 'פחיות'. | K33: ללא שינוי. | L33: SAP Help - Material Groups
A34: 8 | C34: BKLAS | D34: CHAR | E34: 4 | F34: - | G34: Valuation class | H34: מחלקת הערכה
A36: ◆ טבלה T023T - טקסטים לקבוצות חומר (Material group descriptions) | T-codes: OMSF
A37: 9 | B37: T023T | C37: MATKL | D37: CHAR | E37: 9 | F37: PK/FK | G37: Material group | H37: קבוצת חומר | I37: FROM T023T JOIN T023 ON T023T.MATKL = T023.MATKL | J37: תיאורי קבוצות החומר הרב-לשוניים. | K37: ללא שינוי. | L37: SAP Help - Material Groups
A38: 10 | C38: SPRAS | D38: LANG | E38: 1 | F38: PK | G38: Language key | H38: שפה
A39: 11 | C39: WGBEZ | D39: CHAR | E39: 20 | F39: - | G39: Material group description | H39: תיאור קבוצת חומר
A41: ◆ טבלה T399X - פרמטרי בקרת ייצור למפעל (Plant production control parameters) | T-codes: OPL8; SPRO
A42: 12 | B42: T399X | C42: WERKS | D42: CHAR | E42: 4 | F42: PK | G42: Plant | H42: מפעל | I42: FROM AUFK JOIN T399X ON AUFK.WERKS = T399X.WERKS AND AUFK.AUART = T399X.AUART | J42: פרמטרי בקרה לפק"ע לפי מפעל/סוג פק"ע: זמינות, אופק שחרור, פרופיל סטטוס, IDoc. כאן מוגדרת זרימת ה-Control Recipe ל-Zetes/Daymax. | K42: ללא שינוי (Customizing). | L42: SAP Help - Order Type Plant Parameters
A43: 13 | C43: AUART | D43: CHAR | E43: 4 | F43: PK | G43: Order type | H43: סוג פק"ע
A44: 14 | C44: APROFIL | D44: CHAR | E44: 4 | F44: - | G44: Availability check profile | H44: פרופיל בדיקת זמינות
A45: 15 | C45: TERHO | D45: NUMC | E45: 3 | F45: - | G45: Scheduling / release horizon | H45: אופק שחרור
A47: ◆ טבלה TCK03 - וריאנט תמחיר (Costing Variant) (Costing variant) | T-codes: OKKN; SPRO
A48: 16 | B48: TCK03 | C48: KLVAR | D48: CHAR | E48: 4 | F48: PK | G48: Costing variant | H48: וריאנט תמחיר | I48: FROM T399X JOIN TCK03 ON T399X.KLVARP = TCK03.KLVAR | J48: מגדיר את וריאנט התמחיר המתוכנן/בפועל של פק"ע (אסטרטגיית מחיר, אזור). בסיס לחישוב עלות התקן של משקה. | K48: תואם; הערכה ב-Material Ledger/ACDOCA. | L48: SAP Help - Costing Variant
A49: 17 | C49: BWVAR | D49: CHAR | E49: 3 | F49: - | G49: Valuation variant | H49: וריאנט הערכה
A50: 18 | C50: KALAW | D50: CHAR | E50: 2 | F50: - | G50: Costing type | H50: סוג תמחיר
A52: ◆ טבלה T438M - פרמטרי MRP לחומר/מפעל (MRP control parameters) | T-codes: OPPQ; SPRO
A53: 19 | B53: T438M | C53: DISMM | D53: CHAR | E53: 2 | F53: PK | G53: MRP type | H53: סוג MRP | I53: FROM MARC JOIN T438M ON MARC.DISMM = T438M.DISMM | J53: פרמטרי בקרת MRP (סוג תכנון, גודל אצווה) - שולטים בתכנון אוטומטי של חומרי גלם וייצור ב-MRP Live. | K53: MRP Live - חלק מהפרמטרים מותאמים; אמת מול SAP Help. | L53: SAP Help - MRP Parameters
A54: 20 | C54: DISVF | D54: CHAR | E54: 1 | F54: - | G54: MRP procedure | H54: שיטת MRP
A56: ◆ טבלה T003O - סוגי פקודת ייצור (Process Order Types) (Order types (process orders)) | T-codes: COR4; SPRO
A57: 21 | B57: T003O | C57: AUART | D57: CHAR | E57: 4 | F57: PK | G57: Order type | H57: סוג פק"ע | I57: FROM AUFK JOIN T003O ON AUFK.AUART = T003O.AUART | J57: מגדיר סוגי פק"ע ייצור (PI01 תהליך, PI02 שיפוץ) - קטגוריה, טווח מספרים ופרופיל סטטוס. ב-CBC מפריד תהליכי ייצור (ערבול/מילוי) מתהליכי תחזוקה. שחרור הפק"ע מפעיל IDoc LOIPRO לקו. | K57: ללא שינוי (Customizing). | L57: SAP Help - Order Types
A58: 22 | C58: AUTYP | D58: NUMC | E58: 2 | F58: - | G58: Order category (40=process) | H58: קטגוריית פק"ע
A59: 23 | C59: STSMA | D59: CHAR | E59: 8 | F59: FK | G59: Status profile | H59: פרופיל סטטוס
A60: 24 | C60: NUMKI | D60: CHAR | E60: 2 | F60: - | G60: Internal number range | H60: טווח מספרים פנימי
A62: ◆ טבלה TCO01 - פרמטרים תלויי סוג פק"ע (Order Profile) (Order type-dependent parameters) | T-codes: COR4; SPRO
A63: 25 | B63: TCO01 | C63: WERKS | D63: CHAR | E63: 4 | F63: PK | G63: Plant | H63: מפעל | I63: FROM TCO01 JOIN T003O ON TCO01.AUART = T003O.AUART | J63: פרמטרי ברירת מחדל לפק"ע לפי סוג/מפעל: וריאנט תמחיר, פרופיל זמינות, פרופיל שחרור Control Recipe ל-MES. כאן מוגדרת זרימת ההוראות ל-Zetes/Daymax. | K63: ללא שינוי (Customizing). | L63: SAP Help - Order Parameters
A64: 26 | C64: AUART | D64: CHAR | E64: 4 | F64: PK/FK | G64: Order type | H64: סוג פק"ע
A65: 27 | C65: KLVARP | D65: CHAR | E65: 4 | F65: FK | G65: Costing variant (plan) | H65: וריאנט תמחיר מתוכנן
A66: 28 | C66: APROF | D66: CHAR | E66: 4 | F66: - | G66: Availability check profile | H66: פרופיל בדיקת זמינות
A68: ◆ טבלה TJ30 - סטטוסי משתמש בפרופיל (User Status) (User status within profile) | T-codes: BS02/BS03
A69: 29 | B69: TJ30 | C69: STSMA | D69: CHAR | E69: 8 | F69: PK | G69: Status profile | H69: פרופיל סטטוס | I69: FROM JEST JOIN TJ30 ON JEST.STAT = TJ30.ESTAT | J69: מגדיר סטטוסי משתמש מותאמים (למשל 'אושר QA', 'ממתין חומר') וחסימת/התרת תהליכים. ב-CBC אוכף תהליכי עבודה ברמת התא/קו (cell-level) - חוסם שחרור פק"ע עד אישור. | K69: ללא שינוי. | L69: SAP Help - Status Management
A70: 30 | C70: ESTAT | D70: CHAR | E70: 5 | F70: PK | G70: User status | H70: סטטוס משתמש
A71: 31 | C71: VRGNG | D71: CHAR | E71: 8 | F71: - | G71: Business transaction | H71: תהליך עסקי
A72: 32 | C72: ANWND | D72: CHAR | E72: 8 | F72: - | G72: Application (PP) | H72: יישום
A74: ◆ טבלה TJ30T - טקסטים לסטטוסי משתמש (User status texts) | T-codes: BS02/BS03
A75: 33 | B75: TJ30T | C75: STSMA | D75: CHAR | E75: 8 | F75: PK/FK | G75: Status profile | H75: פרופיל סטטוס | I75: FROM TJ30T JOIN TJ30 ON TJ30T.STSMA = TJ30.STSMA AND TJ30T.ESTAT = TJ30.ESTAT | J75: התיאורים הרב-לשוניים (עברית/אנגלית) של סטטוסי המשתמש - חיוני לתצוגה דו-לשונית בלוח הייצור (COIO). | K75: ללא שינוי. | L75: SAP Help - Status Texts
A76: 34 | C76: ESTAT | D76: CHAR | E76: 5 | F76: PK/FK | G76: User status | H76: סטטוס משתמש
A77: 35 | C77: SPRAS | D77: LANG | E77: 1 | F77: PK | G77: Language key | H77: שפה
A78: 36 | C78: TXT04 | D78: CHAR | E78: 4 | F78: - | G78: Short code | H78: קוד מקוצר
A79: 37 | C79: TXT30 | D79: CHAR | E79: 30 | F79: - | G79: Status text | H79: תיאור סטטוס
A81: ◆ טבלה BUT000 - שותף עסקי (BP - השפעת מעבר S/4) (Business Partner general data) | T-codes: BP; (ECC: XK01/MK01)
A82: 38 | B82: BUT000 | C82: PARTNER | D82: CHAR | E82: 10 | F82: PK | G82: Business partner number | H82: מספר שותף עסקי | I82: FROM EKKO JOIN BUT000 ON EKKO.LIFNR = BUT000.PARTNER | J82: ב-S/4HANA ספקי חומרי הגלם/אריזה של CBC מנוהלים כ-Business Partner (BP) במקום ספק קלאסי. נדרש CVI להמרת LFA1->BUT000 לפני ההמרה. כל רכש חומר גלם לייצור מצריך BP פעיל עם תפקיד ספק (FLVN01). | K82: הוחלף - Business Partner חובה (CVI); ראה SAP Note 2265093. | L82: SAP Note 2265093 (BP)
A83: 39 | C83: TYPE | D83: CHAR | E83: 1 | F83: - | G83: BP category | H83: קטגוריית שותף
A84: 40 | C84: BU_GROUP | D84: CHAR | E84: 4 | F84: FK | G84: BP grouping | H84: קבוצת שותף
A85: 41 | C85: BPKIND | D85: CHAR | E85: 4 | F85: - | G85: BP type | H85: סוג שותף
A86: 42 | C86: NAME_ORG1 | D86: CHAR | E86: 40 | F86: - | G86: Organization name | H86: שם ארגון
A88: ◆ טבלה TC22 - מפתחות בקרת תהליך/פעולה (PI Control) (Process/operation control keys config) | T-codes: SPRO; OPL8
A89: 43 | B89: TC22 | C89: STEUS | D89: CHAR | E89: 4 | F89: PK | G89: Control key | H89: מפתח בקרה | I89: FROM PLPO JOIN TC22 ON PLPO.STEUS = TC22.STEUS | J89: הגדרת מפתחות הבקרה (STEUS) הקובעים אם פעולה מפעילה הוראות תהליך (PI), דיווח, תמחיר או רכש חיצוני. לב חיבור ה-PP-PI לאוטומציית הקו. (אמת מול SE11 - מפתחות בקרה גם ב-TC30). | K89: ללא שינוי (Customizing). | L89: SAP Help - Control Keys
A90: 44 | C90: RUECK | D90: CHAR | E90: 1 | F90: - | G90: Confirmation indicator | H90: מחוון דיווח
A91: 45 | C91: BANFK | D91: CHAR | E91: 1 | F91: - | G91: External processing (PReq) | H91: עיבוד חיצוני
A92: 46 | C92: PROZESS | D92: CHAR | E92: 1 | F92: - | G92: Process instruction indicator | H92: מחוון הוראות תהליך

Sheet Cockpit מעקב מיגרציה
A1: ◄ חזרה למסך הראשי | C1: Cockpit מעקב מיגרציה - PP-PI Migration Tracking (Project NEO)
B2: KPI & Summary - סיכום חי (COUNTIF; בסיס מוכן לגרף נייטיב ב-2 קליקים) | K2: Status | L2: Count
B3: =COUNTA($C$8:$C$72) | C3: =COUNTIF($D$8:$D$72,"Done") | D3: =COUNTIF($D$8:$D$72,"Tested") | E3: =COUNTIF($D$8:$D$72,"In analysis")+COUNTIF($D$8:$D$72,"In conversion") | F3: =COUNTIF($D$8:$D$72,"Not started") | G3: =IFERROR(COUNTIF($D$8:$D$72,"Done")/COUNTA($C$8:$C$72),0) | K3: Not started | L3: =COUNTIF($D$8:$D$72,$K3)
B4: סה"כ | C4: Done | D4: Tested | E4: In Progress | F4: Open | G4: % Done | K4: In analysis | L4: =COUNTIF($D$8:$D$72,$K4)
K5: In conversion | L5: =COUNTIF($D$8:$D$72,$K5)
K6: Tested | L6: =COUNTIF($D$8:$D$72,$K6)
A7: מס' (#) | B7: מודול / נושא | C7: טבלה | D7: סטטוס מעבר (Status) | E7: קישור | F7: תיאור | K7: Done | L7: =COUNTIF($D$8:$D$72,$K7)
A8: 1 | B8: 1. נתוני אב חומר ויחידות מידה (Material & UoM) | C8: MARA | D8: Not started | E8: =HYPERLINK("#'"&"1. נתוני אב חומר ויחידות מידה ("&"'!A22","➜ פתח") | F8: נתוני אב חומר כלליים
A9: 2 | B9: 1. נתוני אב חומר ויחידות מידה (Material & UoM) | C9: MAKT | D9: Not started | E9: =HYPERLINK("#'"&"1. נתוני אב חומר ויחידות מידה ("&"'!A32","➜ פתח") | F9: תיאורי חומר (טקסטים)
A10: 3 | B10: 1. נתוני אב חומר ויחידות מידה (Material & UoM) | C10: MARC | D10: Not started | E10: =HYPERLINK("#'"&"1. נתוני אב חומר ויחידות מידה ("&"'!A38","➜ פתח") | F10: נתוני חומר ברמת מפעל
A11: 4 | B11: 1. נתוני אב חומר ויחידות מידה (Material & UoM) | C11: MARD | D11: Not started | E11: =HYPERLINK("#'"&"1. נתוני אב חומר ויחידות מידה ("&"'!A48","➜ פתח") | F11: נתוני חומר ברמת מחסן/מלאי
A12: 5 | B12: 1. נתוני אב חומר ויחידות מידה (Material & UoM) | C12: MARM | D12: Not started | E12: =HYPERLINK("#'"&"1. נתוני אב חומר ויחידות מידה ("&"'!A55","➜ פתח") | F12: המרות יחידות מידה חלופיות
A13: 6 | B13: 1. נתוני אב חומר ויחידות מידה (Material & UoM) | C13: MEAN | D13: Not started | E13: =HYPERLINK("#'"&"1. נתוני אב חומר ויחידות מידה ("&"'!A63","➜ פתח") | F13: ברקודים / EAN לחומר
A14: 7 | B14: 1. נתוני אב חומר ויחידות מידה (Material & UoM) | C14: MBEW | D14: Not started | E14: =HYPERLINK("#'"&"1. נתוני אב חומר ויחידות מידה ("&"'!A70","➜ פתח") | F14: הערכת חומר (Valuation)
A15: 8 | B15: 1. נתוני אב חומר ויחידות מידה (Material & UoM) | C15: MVKE | D15: Not started | E15: =HYPERLINK("#'"&"1. נתוני אב חומר ויחידות מידה ("&"'!A78","➜ פתח") | F15: נתוני חומר ברמת מכירות
A16: 9 | B16: 1. נתוני אב חומר ויחידות מידה (Material & UoM) | C16: MLAN | D16: Not started | E16: =HYPERLINK("#'"&"1. נתוני אב חומר ויחידות מידה ("&"'!A84","➜ פתח") | F16: נתוני מס לחומר (לפי מדינה)
A17: 10 | B17: 1. נתוני אב חומר ויחידות מידה (Material & UoM) | C17: MLGN | D17: Not started | E17: =HYPERLINK("#'"&"1. נתוני אב חומר ויחידות מידה ("&"'!A89","➜ פתח") | F17: נתוני חומר ברמת מחסן (WM)
A18: 11 | B18: 1. נתוני אב חומר ויחידות מידה (Material & UoM) | C18: MLGT | D18: Not started | E18: =HYPERLINK("#'"&"1. נתוני אב חומר ויחידות מידה ("&"'!A95","➜ פתח") | F18: נתוני חומר לפי טיפוס אחסון
A19: 12 | B19: 1. נתוני אב חומר ויחידות מידה (Material & UoM) | C19: MDMA | D19: Not started | E19: =HYPERLINK("#'"&"1. נתוני אב חומר ויחידות מידה ("&"'!A101","➜ פתח") | F19: אזורי MRP לחומר
A20: 13 | B20: 1. נתוני אב חומר ויחידות מידה (Material & UoM) | C20: QMAT | D20: Not started | E20: =HYPERLINK("#'"&"1. נתוני אב חומר ויחידות מידה ("&"'!A107","➜ פתח") | F20: הגדרות בדיקת איכות לחומר
A21: 14 | B21: 1. נתוני אב חומר ויחידות מידה (Material & UoM) | C21: MCH1 | D21: Not started | E21: =HYPERLINK("#'"&"1. נתוני אב חומר ויחידות מידה ("&"'!A113","➜ פתח") | F21: אצוות חומר (Batches)
A22: 15 | B22: 1. נתוני אב חומר ויחידות מידה (Material & UoM) | C22: MCHA | D22: Not started | E22: =HYPERLINK("#'"&"1. נתוני אב חומר ויחידות מידה ("&"'!A122","➜ פתח") | F22: אצוות חומר ברמת מפעל
A23: 16 | B23: 1. נתוני אב חומר ויחידות מידה (Material & UoM) | C23: T006 | D23: Not started | E23: =HYPERLINK("#'"&"1. נתוני אב חומר ויחידות מידה ("&"'!A128","➜ פתח") | F23: יחידות מידה (Customizing)
A24: 17 | B24: 2. עץ מוצר (BOM) | C24: MAST | D24: Not started | E24: =HYPERLINK("#'"&"2. עץ מוצר (BOM)"&"'!A21","➜ פתח") | F24: קישור חומר לעץ מוצר
A25: 18 | B25: 2. עץ מוצר (BOM) | C25: STKO | D25: Not started | E25: =HYPERLINK("#'"&"2. עץ מוצר (BOM)"&"'!A28","➜ פתח") | F25: כותרת עץ מוצר
A26: 19 | B26: 2. עץ מוצר (BOM) | C26: STPO | D26: Not started | E26: =HYPERLINK("#'"&"2. עץ מוצר (BOM)"&"'!A36","➜ פתח") | F26: פריטי עץ מוצר (רכיבים)
A27: 20 | B27: 2. עץ מוצר (BOM) | C27: STAS | D27: Not started | E27: =HYPERLINK("#'"&"2. עץ מוצר (BOM)"&"'!A47","➜ פתח") | F27: בחירת פריטי עץ מוצר
A28: 21 | B28: 2. עץ מוצר (BOM) | C28: STZU | D28: Not started | E28: =HYPERLINK("#'"&"2. עץ מוצר (BOM)"&"'!A54","➜ פתח") | F28: טבלת היסטוריה/קישור לעץ מוצר
A29: 22 | B29: 2. עץ מוצר (BOM) | C29: STPU | D29: Not started | E29: =HYPERLINK("#'"&"2. עץ מוצר (BOM)"&"'!A60","➜ פתח") | F29: טקסטים ארוכים לפריט עץ מוצר
A30: 23 | B30: 2. עץ מוצר (BOM) | C30: KDST | D30: Not started | E30: =HYPERLINK("#'"&"2. עץ מוצר (BOM)"&"'!A65","➜ פתח") | F30: שימוש עץ מוצר בהזמנת לקוח
A31: 24 | B31: 3. מתכון ייצור ופעולות (Master Recipe) | C31: PLKO | D31: Not started | E31: =HYPERLINK("#'"&"3. מתכון ייצור ופעולות (Master "&"'!A21","➜ פתח") | F31: כותרת מתכון ייצור / רשימת פעולות
A32: 25 | B32: 3. מתכון ייצור ופעולות (Master Recipe) | C32: PLPO | D32: Not started | E32: =HYPERLINK("#'"&"3. מתכון ייצור ופעולות (Master "&"'!A30","➜ פתח") | F32: פעולות/פאזות במתכון
A33: 26 | B33: 3. מתכון ייצור ופעולות (Master Recipe) | C33: PLAS | D33: Not started | E33: =HYPERLINK("#'"&"3. מתכון ייצור ופעולות (Master "&"'!A41","➜ פתח") | F33: שיוך/בחירת פעולות לרשימה
A34: 27 | B34: 3. מתכון ייצור ופעולות (Master Recipe) | C34: PLFL | D34: Not started | E34: =HYPERLINK("#'"&"3. מתכון ייצור ופעולות (Master "&"'!A49","➜ פתח") | F34: רצפים במתכון
A35: 28 | B35: 3. מתכון ייצור ופעולות (Master Recipe) | C35: PLMZ | D35: Not started | E35: =HYPERLINK("#'"&"3. מתכון ייצור ופעולות (Master "&"'!A55","➜ פתח") | F35: שיוך רכיבים לפעולות
A36: 29 | B36: 3. מתכון ייצור ופעולות (Master Recipe) | C36: PLMK | D36: Not started | E36: =HYPERLINK("#'"&"3. מתכון ייצור ופעולות (Master "&"'!A62","➜ פתח") | F36: מאפייני בדיקה במתכון
A37: 30 | B37: 3. מתכון ייצור ופעולות (Master Recipe) | C37: MAPL | D37: Not started | E37: =HYPERLINK("#'"&"3. מתכון ייצור ופעולות (Master "&"'!A70","➜ פתח") | F37: שיוך חומר למתכון/רשימת פעולות
A38: 31 | B38: 3. מתכון ייצור ופעולות (Master Recipe) | C38: FHMI | D38: Not started | E38: =HYPERLINK("#'"&"3. מתכון ייצור ופעולות (Master "&"'!A77","➜ פתח") | F38: שיוך כלי עזר ייצור (PRT) לפעולה
A39: 32 | B39: 3. מתכון ייצור ופעולות (Master Recipe) | C39: PLZU | D39: Not started | E39: =HYPERLINK("#'"&"3. מתכון ייצור ופעולות (Master "&"'!A83","➜ פתח") | F39: קישור היסטוריית רשימת פעולות
A40: 33 | B40: 3. מתכון ייצור ופעולות (Master Recipe) | C40: TC60 | D40: Not started | E40: =HYPERLINK("#'"&"3. מתכון ייצור ופעולות (Master "&"'!A88","➜ פתח") | F40: מאפייני הוראות תהליך (PI)
A41: 34 | B41: 3. מתכון ייצור ופעולות (Master Recipe) | C41: TCA01 | D41: Not started | E41: =HYPERLINK("#'"&"3. מתכון ייצור ופעולות (Master "&"'!A93","➜ פתח") | F41: פרופיל רשימת פעולות (Customizing)
A42: 35 | B42: 4. גרסאות ייצור (Production Versions - חובה ב-S/4) | C42: MKAL | D42: Not started | E42: =HYPERLINK("#'"&"4. גרסאות ייצור (Production Ver"&"'!A19","➜ פתח") | F42: גרסאות ייצור לחומר
A43: 36 | B43: 5. משאבים / מרכזי עבודה (Resources) | C43: CRHD | D43: Not started | E43: =HYPERLINK("#'"&"5. משאבים מרכזי עבודה (Resourc"&"'!A20","➜ פתח") | F43: כותרת משאב / מרכז עבודה
A44: 37 | B44: 5. משאבים / מרכזי עבודה (Resources) | C44: CRTX | D44: Not started | E44: =HYPERLINK("#'"&"5. משאבים מרכזי עבודה (Resourc"&"'!A29","➜ פתח") | F44: טקסטים של משאב
A45: 38 | B45: 5. משאבים / מרכזי עבודה (Resources) | C45: CRCO | D45: Not started | E45: =HYPERLINK("#'"&"5. משאבים מרכזי עבודה (Resourc"&"'!A35","➜ פתח") | F45: שיוך משאב למרכז עלות
A46: 39 | B46: 5. משאבים / מרכזי עבודה (Resources) | C46: CRCA | D46: Not started | E46: =HYPERLINK("#'"&"5. משאבים מרכזי עבודה (Resourc"&"'!A43","➜ פתח") | F46: הקצאת קיבולת למשאב
A47: 40 | B47: 5. משאבים / מרכזי עבודה (Resources) | C47: KAKO | D47: Not started | E47: =HYPERLINK("#'"&"5. משאבים מרכזי עבודה (Resourc"&"'!A49","➜ פתח") | F47: כותרת קיבולת
A48: 41 | B48: 5. משאבים / מרכזי עבודה (Resources) | C48: CRFH | D48: Not started | E48: =HYPERLINK("#'"&"5. משאבים מרכזי עבודה (Resourc"&"'!A55","➜ פתח") | F48: אב כלי עזר ייצור (PRT)
A49: 42 | B49: 5. משאבים / מרכזי עבודה (Resources) | C49: CRVD_A | D49: Not started | E49: =HYPERLINK("#'"&"5. משאבים מרכזי עבודה (Resourc"&"'!A61","➜ פתח") | F49: ברירות מחדל למשאב (PI)
A50: 43 | B50: 5. משאבים / מרכזי עבודה (Resources) | C50: CSLA | D50: Not started | E50: =HYPERLINK("#'"&"5. משאבים מרכזי עבודה (Resourc"&"'!A66","➜ פתח") | F50: סוגי פעילות למרכז עבודה
A51: 44 | B51: 5. משאבים / מרכזי עבודה (Resources) | C51: KAZT | D51: Not started | E51: =HYPERLINK("#'"&"5. משאבים מרכזי עבודה (Resourc"&"'!A71","➜ פתח") | F51: מרווחי קיבולת זמינה
A52: 45 | B52: 6. פק"ע ייצור ומתכון בקרה (Process Order) | C52: AUFK | D52: Not started | E52: =HYPERLINK("#'"&"6. פק"ע ייצור ומתכון בקרה (Proc"&"'!A22","➜ פתח") | F52: נתוני אב של פקודת ייצור
A53: 46 | B53: 6. פק"ע ייצור ומתכון בקרה (Process Order) | C53: AFKO | D53: Not started | E53: =HYPERLINK("#'"&"6. פק"ע ייצור ומתכון בקרה (Proc"&"'!A29","➜ פתח") | F53: כותרת פקודת ייצור
A54: 47 | B54: 6. פק"ע ייצור ומתכון בקרה (Process Order) | C54: AFPO | D54: Not started | E54: =HYPERLINK("#'"&"6. פק"ע ייצור ומתכון בקרה (Proc"&"'!A37","➜ פתח") | F54: פריט פקודת ייצור
A55: 48 | B55: 6. פק"ע ייצור ומתכון בקרה (Process Order) | C55: AFVC | D55: Not started | E55: =HYPERLINK("#'"&"6. פק"ע ייצור ומתכון בקרה (Proc"&"'!A44","➜ פתח") | F55: פעולות פקודת הייצור
A56: 49 | B56: 6. פק"ע ייצור ומתכון בקרה (Process Order) | C56: RESB | D56: Not started | E56: =HYPERLINK("#'"&"6. פק"ע ייצור ומתכון בקרה (Proc"&"'!A52","➜ פתח") | F56: הזמנת רכיבים לפק"ע
A57: 50 | B57: 6. פק"ע ייצור ומתכון בקרה (Process Order) | C57: AFRU | D57: Not started | E57: =HYPERLINK("#'"&"6. פק"ע ייצור ומתכון בקרה (Proc"&"'!A60","➜ פתח") | F57: דיווחי ביצוע פק"ע
A58: 51 | B58: 6. פק"ע ייצור ומתכון בקרה (Process Order) | C58: AFFH | D58: Not started | E58: =HYPERLINK("#'"&"6. פק"ע ייצור ומתכון בקרה (Proc"&"'!A67","➜ פתח") | F58: שיוך PRT לפק"ע
A59: 52 | B59: 6. פק"ע ייצור ומתכון בקרה (Process Order) | C59: AFFL | D59: Not started | E59: =HYPERLINK("#'"&"6. פק"ע ייצור ומתכון בקרה (Proc"&"'!A72","➜ פתח") | F59: רצפי פעולות בפק"ע
A60: 53 | B60: 7. קונפיגורציה (Customizing) | C60: T134 | D60: Not started | E60: =HYPERLINK("#'"&"7. קונפיגורציה (Customizing)"&"'!A22","➜ פתח") | F60: סוגי חומר (Customizing)
A61: 54 | B61: 7. קונפיגורציה (Customizing) | C61: T134T | D61: Not started | E61: =HYPERLINK("#'"&"7. קונפיגורציה (Customizing)"&"'!A27","➜ פתח") | F61: טקסטים לסוגי חומר
A62: 55 | B62: 7. קונפיגורציה (Customizing) | C62: T023 | D62: Not started | E62: =HYPERLINK("#'"&"7. קונפיגורציה (Customizing)"&"'!A32","➜ פתח") | F62: קבוצות חומר (Customizing)
A63: 56 | B63: 7. קונפיגורציה (Customizing) | C63: T023T | D63: Not started | E63: =HYPERLINK("#'"&"7. קונפיגורציה (Customizing)"&"'!A36","➜ פתח") | F63: טקסטים לקבוצות חומר
A64: 57 | B64: 7. קונפיגורציה (Customizing) | C64: T399X | D64: Not started | E64: =HYPERLINK("#'"&"7. קונפיגורציה (Customizing)"&"'!A41","➜ פתח") | F64: פרמטרי בקרת ייצור למפעל
A65: 58 | B65: 7. קונפיגורציה (Customizing) | C65: TCK03 | D65: Not started | E65: =HYPERLINK("#'"&"7. קונפיגורציה (Customizing)"&"'!A47","➜ פתח") | F65: וריאנט תמחיר (Costing Variant)
A66: 59 | B66: 7. קונפיגורציה (Customizing) | C66: T438M | D66: Not started | E66: =HYPERLINK("#'"&"7. קונפיגורציה (Customizing)"&"'!A52","➜ פתח") | F66: פרמטרי MRP לחומר/מפעל
A67: 60 | B67: 7. קונפיגורציה (Customizing) | C67: T003O | D67: Not started | E67: =HYPERLINK("#'"&"7. קונפיגורציה (Customizing)"&"'!A56","➜ פתח") | F67: סוגי פקודת ייצור (Process Order Types)
A68: 61 | B68: 7. קונפיגורציה (Customizing) | C68: TCO01 | D68: Not started | E68: =HYPERLINK("#'"&"7. קונפיגורציה (Customizing)"&"'!A62","➜ פתח") | F68: פרמטרים תלויי סוג פק"ע (Order Profile)
A69: 62 | B69: 7. קונפיגורציה (Customizing) | C69: TJ30 | D69: Not started | E69: =HYPERLINK("#'"&"7. קונפיגורציה (Customizing)"&"'!A68","➜ פתח") | F69: סטטוסי משתמש בפרופיל (User Status)
A70: 63 | B70: 7. קונפיגורציה (Customizing) | C70: TJ30T | D70: Not started | E70: =HYPERLINK("#'"&"7. קונפיגורציה (Customizing)"&"'!A74","➜ פתח") | F70: טקסטים לסטטוסי משתמש
A71: 64 | B71: 7. קונפיגורציה (Customizing) | C71: BUT000 | D71: Not started | E71: =HYPERLINK("#'"&"7. קונפיגורציה (Customizing)"&"'!A81","➜ פתח") | F71: שותף עסקי (BP - השפעת מעבר S/4)
A72: 65 | B72: 7. קונפיגורציה (Customizing) | C72: TC22 | D72: Not started | E72: =HYPERLINK("#'"&"7. קונפיגורציה (Customizing)"&"'!A88","➜ פתח") | F72: מפתחות בקרת תהליך/פעולה (PI Control)

Sheet ER - Join Map
A1: ◄ חזרה למסך הראשי | C1: ER - Join Map - JOIN ON (SQL / CDS Views) · CBC NEO
A2: מס' (#) | B2: טבלה (Child) | C2: JOIN ON (SQL / CDS Views Syntax) | D2: תיאור
A3: 1 | B3: MAKT | C3: FROM MAKT JOIN MARA ON MAKT.MATNR = MARA.MATNR | D3: תיאורי חומר (טקסטים)
A4: 2 | B4: MARC | C4: FROM MARC JOIN MARA ON MARC.MATNR = MARA.MATNR | D4: נתוני חומר ברמת מפעל
A5: 3 | B5: MARD | C5: FROM MARD JOIN MARC ON MARD.MATNR = MARC.MATNR AND MARD.WERKS = MARC.WERKS | D5: נתוני חומר ברמת מחסן/מלאי
A6: 4 | B6: MARM | C6: FROM MARM JOIN MARA ON MARM.MATNR = MARA.MATNR | D6: המרות יחידות מידה חלופיות
A7: 5 | B7: MEAN | C7: FROM MEAN JOIN MARA ON MEAN.MATNR = MARA.MATNR | D7: ברקודים / EAN לחומר
A8: 6 | B8: MBEW | C8: FROM MBEW JOIN MARA ON MBEW.MATNR = MARA.MATNR | D8: הערכת חומר (Valuation)
A9: 7 | B9: MVKE | C9: FROM MVKE JOIN MARA ON MVKE.MATNR = MARA.MATNR | D9: נתוני חומר ברמת מכירות
A10: 8 | B10: MLAN | C10: FROM MLAN JOIN MARA ON MLAN.MATNR = MARA.MATNR | D10: נתוני מס לחומר (לפי מדינה)
A11: 9 | B11: MLGN | C11: FROM MLGN JOIN MARA ON MLGN.MATNR = MARA.MATNR | D11: נתוני חומר ברמת מחסן (WM)
A12: 10 | B12: MLGT | C12: FROM MLGT JOIN MLGN ON MLGT.MATNR = MLGN.MATNR AND MLGT.LGNUM = MLGN.LGNUM | D12: נתוני חומר לפי טיפוס אחסון
A13: 11 | B13: MDMA | C13: FROM MDMA JOIN MARC ON MDMA.MATNR = MARC.MATNR AND MDMA.WERKS = MARC.WERKS | D13: אזורי MRP לחומר
A14: 12 | B14: QMAT | C14: FROM QMAT JOIN MARC ON QMAT.MATNR = MARC.MATNR AND QMAT.WERKS = MARC.WERKS | D14: הגדרות בדיקת איכות לחומר
... A64: 62 | B64: TC22 | C64: FROM PLPO JOIN TC22 ON PLPO.STEUS = TC22.STEUS | D64: מפתחות בקרת תהליך/פעולה (PI Control)
